ParallelFilter_L=3/filter.sv
`timescale 1ns / 1ps

module filter(
  input logic clk,
  input logic rst,
  input logic signed [31:0] x_in,
  input logic signed [31:0] x_in1,
  input logic signed [31:0] x_in2,
  output logic signed [63:0] y_out,
  output logic signed [63:0] y_out1,
  output logic signed [63:0] y_out2
);

parameter NUM_TAPS = 102;

logic signed [31:0] coeffs [102:0];

always_comb begin 
  coeffs[0] = 32'b11111111111110000010000011101100;
  coeffs[1] = 32'b11111111111000010011001010000001;
  coeffs[2] = 32'b11111111101011100010111001111001;
  coeffs[3] = 32'b11111111010011101111001000101101;
  coeffs[4] = 32'b11111110101101101111000110001010;
  coeffs[5] = 32'b11111101110111110111100010111000;
  coeffs[6] = 32'b11111100110100010100110110110111;
  coeffs[7] = 32'b11111011101001011101101101010111;
  coeffs[8] = 32'b11111010100010100111011001000011;
  coeffs[9] = 32'b11111001101101111111100111111111;
  coeffs[10] = 32'b11111001011010011101011111111110;
  coeffs[11] = 32'b11111001110010111111111101010011;
  coeffs[12] = 32'b11111010111011010101111011010111;
  coeffs[13] = 32'b11111100101100101101111001110001;
  coeffs[14] = 32'b11111110110110000001000110111110;
  coeffs[15] = 32'b00000000111110000010100110001000;
  coeffs[16] = 32'b00000010101001011010110110000000;
  coeffs[17] = 32'b00000011100001010010111010001011;
  coeffs[18] = 32'b00000011011010011010010100001110;
  coeffs[19] = 32'b00000010011000111100101011100000;
  coeffs[20] = 32'b00000000110000110111000110011101;
  coeffs[21] = 32'b11111111000000110111110001011111;
  coeffs[22] = 32'b11111101101010010011111101110010;
  coeffs[23] = 32'b11111101000110111111001100000111;
  coeffs[24] = 32'b11111101100001001011010110000110;
  coeffs[25] = 32'b11111110101111100111010001101110;
  coeffs[26] = 32'b00000000010111111110001101011110;
  coeffs[27] = 32'b00000001110110101110101010000111;
  coeffs[28] = 32'b00000010101010111010000001111100;
  coeffs[29] = 32'b00000010100001010010001000001011;
  coeffs[30] = 32'b00000001011011110110001011011000;
  coeffs[31] = 32'b11111111110010000001100101001000;
  coeffs[32] = 32'b11111110001001101010010111101101;
  coeffs[33] = 32'b11111101001010001001010011000111;
  coeffs[34] = 32'b11111101001110010001111000001100;
  coeffs[35] = 32'b11111110011001011000100000110110;
  coeffs[36] = 32'b00000000010100001011100010001100;
  coeffs[37] = 32'b00000010010010111000011111011011;
  coeffs[38] = 32'b00000011100011011111000110001011;
  coeffs[39] = 32'b00000011011111101001010101110110;
  coeffs[40] = 32'b00000001111100011111001111010010;
  coeffs[41] = 32'b11111111010010010111100110101101;
  coeffs[42] = 32'b11111100011001011001110000001110;
  coeffs[43] = 32'b11111010011010101010011011100011;
  coeffs[44] = 32'b11111010011010001100111111001111;
  coeffs[45] = 32'b11111101000000010110011101000010;
  coeffs[46] = 32'b00000010001001101111111101000100;
  coeffs[47] = 32'b00001001000011100100110011010111;
  coeffs[48] = 32'b00010000010110000000010110001000;
  coeffs[49] = 32'b00010110011010010110100111011111;
  coeffs[50] = 32'b00011001110110101011101000100111;
  coeffs[51] = 32'b00011001110110101011101000100111;
  coeffs[52] = 32'b00010110011010010110100111011111;
  coeffs[53] = 32'b00010000010110000000010110001000;
  coeffs[54] = 32'b00001001000011100100110011010111;
  coeffs[55] = 32'b00000010001001101111111101000100;
  coeffs[56] = 32'b11111101000000010110011101000010;
  coeffs[57] = 32'b11111010011010001100111111001111;
  coeffs[58] = 32'b11111010011010101010011011100011;
  coeffs[59] = 32'b11111100011001011001110000001110;
  coeffs[60] = 32'b11111111010010010111100110101101;
  coeffs[61] = 32'b00000001111100011111001111010010;
  coeffs[62] = 32'b00000011011111101001010101110110;
  coeffs[63] = 32'b00000011100011011111000110001011;
  coeffs[64] = 32'b00000010010010111000011111011011;
  coeffs[65] = 32'b00000000010100001011100010001100;
  coeffs[66] = 32'b11111110011001011000100000110110;
  coeffs[67] = 32'b11111101001110010001111000001100;
  coeffs[68] = 32'b11111101001010001001010011000111;
  coeffs[69] = 32'b11111110001001101010010111101101;
  coeffs[70] = 32'b11111111110010000001100101001000;
  coeffs[71] = 32'b00000001011011110110001011011000;
  coeffs[72] = 32'b00000010100001010010001000001011;
  coeffs[73] = 32'b00000010101010111010000001111100;
  coeffs[74] = 32'b00000001110110101110101010000111;
  coeffs[75] = 32'b00000000010111111110001101011110;
  coeffs[76] = 32'b11111110101111100111010001101110;
  coeffs[77] = 32'b11111101100001001011010110000110;
  coeffs[78] = 32'b11111101000110111111001100000111;
  coeffs[79] = 32'b11111101101010010011111101110010;
  coeffs[80] = 32'b11111111000000110111110001011111;
  coeffs[81] = 32'b00000000110000110111000110011101;
  coeffs[82] = 32'b00000010011000111100101011100000;
  coeffs[83] = 32'b00000011011010011010010100001110;
  coeffs[84] = 32'b00000011100001010010111010001011;
  coeffs[85] = 32'b00000010101001011010110110000000;
  coeffs[86] = 32'b00000000111110000010100110001000;
  coeffs[87] = 32'b11111110110110000001000110111110;
  coeffs[88] = 32'b11111100101100101101111001110001;
  coeffs[89] = 32'b11111010111011010101111011010111;
  coeffs[90] = 32'b11111001110010111111111101010011;
  coeffs[91] = 32'b11111001011010011101011111111110;
  coeffs[92] = 32'b11111001101101111111100111111111;
  coeffs[93] = 32'b11111010100010100111011001000011;
  coeffs[94] = 32'b11111011101001011101101101010111;
  coeffs[95] = 32'b11111100110100010100110110110111;
  coeffs[96] = 32'b11111101110111110111100010111000;
  coeffs[97] = 32'b11111110101101101111000110001010;
  coeffs[98] = 32'b11111111010011101111001000101101;
  coeffs[99] = 32'b11111111101011100010111001111001;
  coeffs[100] = 32'b11111111111000010011001010000001;
  coeffs[101] = 32'b11111111111110000010000011101100;
end

// Instantiate sample registers
logic signed [31:0] x_3k_samples [(NUM_TAPS / 3) - 1:0];
logic signed [31:0] x_3k1_samples [(NUM_TAPS / 3) - 1:0];
logic signed [31:0] x_3k2_samples [(NUM_TAPS / 3) - 1:0];

// Initialize intermediate computations to be accessed by various function units
// in the filter
logic signed [63:0] h0, h1, h2, h01, h12, h012, h2_delay, h12minh1_delay;  
logic signed [63:0] h01minh1, h12minh1; 

// Instantiate adders for intermediate computations
assign h12minh1 = h12 - h1;
assign h01minh1 = h01 - h1;

always_ff @(posedge clk or posedge rst) begin
  if (rst) begin
    // Clear the delay units
    h2_delay <= 0;
    h12minh1_delay <= 0;
    for (int i=0; i < NUM_TAPS/3-1; i=i+1) begin
      // Clear the sample registers
      x_3k_samples[i] <= 0;
      x_3k1_samples[i] <= 0;
      x_3k2_samples[i] <= 0;
    end 
  end else begin
    for (int i=NUM_TAPS/3-1; i > 0; i=i-1) begin
      // Shift samples
      x_3k_samples[i] <= x_3k_samples[i-1];
      x_3k1_samples[i] <= x_3k1_samples[i-1];
      x_3k2_samples[i] <= x_3k2_samples[i-1];
    end
    // Take in new samples
    x_3k_samples[0] <= x_in;
    x_3k1_samples[0] <= x_in1;
    x_3k2_samples[0] <= x_in2;

    // push delay signals through their delay units
    h2_delay <= h2;
    h12minh1_delay <= h12minh1;
  end
end

always_comb begin
  h0 = 0;
  h1 = 0;
  h2 = 0;
  h01 = 0;
  h12 = 0;
  h012 = 0;
  
  for (int i=0; i <= (NUM_TAPS/3) - 1; i=i+1) begin
    // Perform multiplication with coefficients and accumulations in all three
    // paths
    h0 += x_3k_samples[i] * coeffs[3*i];
    h1 += x_3k1_samples[i] * coeffs[3*i+1];
    h2 += x_3k2_samples[i] * coeffs[3*i+2];

    h01 += (x_3k_samples[i] + x_3k1_samples[i]) * (coeffs[3*i] + coeffs[3*i+1]); 
    h12 += (x_3k1_samples[i] + x_3k2_samples[i]) * (coeffs[3*i+1] + coeffs[3*i+2]); 
    h012 += (x_3k_samples[i] + x_3k1_samples[i] + x_3k2_samples[i]) * (coeffs[3*i] + coeffs[3*i+1] + coeffs[3*i+2]); 
  end
end

// Perform final summations and output the filtered data
assign y_out = (h0 - h2_delay + h12minh1_delay) >>> 31;
assign y_out1 = (h01minh1 - h0 - h2_delay) >>> 31;
assign y_out2 = (h012 - h01minh1 - h12minh1) >>> 31;

endmodule

ParallelFilter_L=3/filter_tb.sv
`timescale 1ns / 1ps

module filter_tb;

  logic clk;
  logic rst;
  logic signed [31:0] x_in, x_in1, x_in2;
  logic signed [63:0] y_out, y_out1, y_out2;

  parameter CLK_PERIOD = 0.5; // 2GHz Clock
  parameter NUM_SAMPLES = 1000;

  filter uut(
    .clk(clk),
    .rst(rst),
    .x_in(x_in),
    .x_in1(x_in1),
    .x_in2(x_in2),
    .y_out(y_out),
    .y_out1(y_out1),
    .y_out2(y_out2)
  );


  // Start the clock
  initial begin
    clk = 0;
    forever #(CLK_PERIOD / 2) clk = ~clk;
  end

  integer file, status;
  integer sample_count;

  logic signed [31:0] sample_data, sample_data1, sample_data2;

  initial begin
    $dumpfile("filter_tb.vcd");
    $dumpvars(0, filter_tb);

    rst = 1;
    x_in = 0;
    sample_count = 0;

    // Open the raw signal data
    file = $fopen("../Python/InputSignals/cosine_wave_100MHz_500MHz.bin", "rb");
    if (file == 0) begin
        $display("Error: Unable to open file!");
        $finish;
    end

    #20 rst = 0;

    // Read and feed samples to the pipeline
    while (sample_count < NUM_SAMPLES) begin
      status = $fread(sample_data, file);
      if (status == 0) begin
        $display("Error: End of file reached or read error!");
        $finish;
      end
      
      status = $fread(sample_data1, file);
      if (status == 0) begin
        $display("Error: End of file reached or read error!");
        $finish;
      end
      
      status = $fread(sample_data2, file);
      if (status == 0) begin
        $display("Error: End of file reached or read error!");
        $finish;
      end

      x_in = sample_data;
      x_in1 = sample_data1;
      x_in2 = sample_data2;
      sample_count = sample_count + 3;
      #CLK_PERIOD;
    end

    $fclose(file);
    #100 $finish;
  end

endmodule

ParallelFilter_L=3/filter_tb.vcd
$date
	Wed Mar 19 01:41:06 2025
$end
$version
	Icarus Verilog
$end
$timescale
	1ps
$end
$scope module filter_tb $end
$var wire 64 ! y_out2 [63:0] $end
$var wire 64 " y_out1 [63:0] $end
$var wire 64 # y_out [63:0] $end
$var real 1 $ CLK_PERIOD $end
$var parameter 32 % NUM_SAMPLES $end
$var reg 1 & clk $end
$var reg 1 ' rst $end
$var reg 32 ( sample_data [31:0] $end
$var reg 32 ) sample_data1 [31:0] $end
$var reg 32 * sample_data2 [31:0] $end
$var reg 32 + x_in [31:0] $end
$var reg 32 , x_in1 [31:0] $end
$var reg 32 - x_in2 [31:0] $end
$var integer 32 . file [31:0] $end
$var integer 32 / sample_count [31:0] $end
$var integer 32 0 status [31:0] $end
$scope module uut $end
$var wire 1 & clk $end
$var wire 1 ' rst $end
$var wire 32 1 x_in [31:0] $end
$var wire 32 2 x_in1 [31:0] $end
$var wire 32 3 x_in2 [31:0] $end
$var wire 64 4 y_out2 [63:0] $end
$var wire 64 5 y_out1 [63:0] $end
$var wire 64 6 y_out [63:0] $end
$var wire 64 7 h12minh1 [63:0] $end
$var wire 64 8 h01minh1 [63:0] $end
$var parameter 32 9 NUM_TAPS $end
$var reg 64 : h0 [63:0] $end
$var reg 64 ; h01 [63:0] $end
$var reg 64 < h012 [63:0] $end
$var reg 64 = h1 [63:0] $end
$var reg 64 > h12 [63:0] $end
$var reg 64 ? h12minh1_delay [63:0] $end
$var reg 64 @ h2 [63:0] $end
$var reg 64 A h2_delay [63:0] $end
$scope begin $ivl_for_loop0 $end
$var integer 32 B i [31:0] $end
$upscope $end
$scope begin $ivl_for_loop1 $end
$var integer 32 C i [31:0] $end
$upscope $end
$scope begin $ivl_for_loop2 $end
$var integer 32 D i [31:0] $end
$upscope $end
$upscope $end
$upscope $end
$enddefinitions $end
$comment Show the parameter values. $end
$dumpall
b1100110 9
b1111101000 %
r0.5 $
$end
#0
$dumpvars
b100010 D
b0 C
b100001 B
b0 A
bx @
b0 ?
bx >
bx =
bx <
bx ;
bx :
bx 8
bx 7
bx 6
bx 5
bx 4
bx 3
bx 2
b0 1
bx 0
b0 /
b10000000000000000000000000000011 .
bx -
bx ,
b0 +
bx *
bx )
bx (
1'
0&
bx #
bx "
bx !
$end
#250
b100001 B
1&
#500
0&
#750
b100001 B
1&
#1000
0&
#1250
b100001 B
1&
#1500
0&
#1750
b100001 B
1&
#2000
0&
#2250
b100001 B
1&
#2500
0&
#2750
b100001 B
1&
#3000
0&
#3250
b100001 B
1&
#3500
0&
#3750
b100001 B
1&
#4000
0&
#4250
b100001 B
1&
#4500
0&
#4750
b100001 B
1&
#5000
0&
#5250
b100001 B
1&
#5500
0&
#5750
b100001 B
1&
#6000
0&
#6250
b100001 B
1&
#6500
0&
#6750
b100001 B
1&
#7000
0&
#7250
b100001 B
1&
#7500
0&
#7750
b100001 B
1&
#8000
0&
#8250
b100001 B
1&
#8500
0&
#8750
b100001 B
1&
#9000
0&
#9250
b100001 B
1&
#9500
0&
#9750
b100001 B
1&
#10000
0&
#10250
b100001 B
1&
#10500
0&
#10750
b100001 B
1&
#11000
0&
#11250
b100001 B
1&
#11500
0&
#11750
b100001 B
1&
#12000
0&
#12250
b100001 B
1&
#12500
0&
#12750
b100001 B
1&
#13000
0&
#13250
b100001 B
1&
#13500
0&
#13750
b100001 B
1&
#14000
0&
#14250
b100001 B
1&
#14500
0&
#14750
b100001 B
1&
#15000
0&
#15250
b100001 B
1&
#15500
0&
#15750
b100001 B
1&
#16000
0&
#16250
b100001 B
1&
#16500
0&
#16750
b100001 B
1&
#17000
0&
#17250
b100001 B
1&
#17500
0&
#17750
b100001 B
1&
#18000
0&
#18250
b100001 B
1&
#18500
0&
#18750
b100001 B
1&
#19000
0&
#19250
b100001 B
1&
#19500
0&
#19750
b100001 B
1&
#20000
0&
b11 /
b11110011110001101110111100111000 -
b11110011110001101110111100111000 3
b111100110111100001110000100110 ,
b111100110111100001110000100110 2
b1111111111111111111111111111111 +
b1111111111111111111111111111111 1
b11110011110001101110111100111000 *
b111100110111100001110000100110 )
b100 0
b1111111111111111111111111111111 (
0'
#20250
b1111111111111111111111111111111111111111101000000100100100011110 !
b1111111111111111111111111111111111111111101000000100100100011110 4
b100010 D
b1111111110101100110110111001111110000000000011010001001010001110 <
b1111111111110001111011000111011010111100001000001011111010100110 7
b1111111111101010100110011001001101100000111100100101100111001100 >
b1111111111101010110010101001100101111111001111010101111110011011 8
b1111111111100011011101111011011000100100000011101111101011000001 ;
b11111010000000111101011000000100110010000101111000 @
b1111111111111000101011010001110010100100110100011001101100100110 =
b1111111111111100000100000111011000000000000001111101111100010100 :
bx ?
bx A
b0 C
1&
#20500
0&
b110 /
b0 -
b0 3
b1010011110001101110111100110110 ,
b1010011110001101110111100110110 2
b100101100111100100011000001000 +
b100101100111100100011000001000 1
b0 *
b1010011110001101110111100110110 )
b100101100111100100011000001000 (
#20750
b1111111111111111111111111111111111111101001001111011001001010010 !
b1111111111111111111111111111111111111101001001111011001001010010 4
b1111111111111111111111111111111111111111001010001010101011000100 #
b1111111111111111111111111111111111111111001010001010101011000100 6
b1111111111111111111111111111111111111110010011001011101101010101 "
b1111111111111111111111111111111111111110010011001011101101010101 5
b100010 D
b1111110011110001111001101111010100100111010010100110110100000111 <
b1111111100110101001001011010010011100101011110011011010011111000 >
b1111111001111000010001010100001010011100010111001011001011011001 ;
b11001111111111011100100110000111001100011000001000000 @
b1111111110001101011101110001011100101011110011011010110001000110 7
b1111111011010000100101101011010011100010101100001010101000100111 8
b1111111110100111101011101000110110111001101011000000100010110010 =
b1111111110100110010100001111101011000111000110101001110100110011 :
b1111111111110001111011000111011010111100001000001011111010100110 ?
b11111010000000111101011000000100110010000101111000 A
b0 C
1&
#21000
0&
b1001 /
b1100001110010001000011001000 -
b1100001110010001000011001000 3
b11011010011000011011100111111000 ,
b11011010011000011011100111111000 2
b10101100001110010001000011001010 +
b10101100001110010001000011001010 1
b1100001110010001000011001000 *
b11011010011000011011100111111000 )
b10101100001110010001000011001010 (
#21250
b1111111111111111111111111111111111110111100011001110011010010110 !
b1111111111111111111111111111111111110111100011001110011010010110 4
b1111111111111111111111111111111111111011100010010101101001101000 #
b1111111111111111111111111111111111111011100010010101101001101000 6
b1111111111111111111111111111111111111001001100000101010011000110 "
b1111111111111111111111111111111111111001001100000101010011000110 5
b100010 D
b1111010101001001111010001100101100001100110111001000000101001011 <
b1111110100010000000001011010100011111011111011011001101111111000 >
b1111100110010011010100000000111010000011101101101011101011110010 ;
b111110110100011110110011001011011100010100101000110000 @
b1111111010000000000101011000110100110010100000111001100111111010 7
b1111101100000011010111111111001010111010010011001011100011110100 8
b1111111010001111111100000001101111001001011010100000000111111110 =
b1111111001010001001101011101011001101101000010010100101111101001 :
b1111111110001101011101110001011100101011110011011010110001000110 ?
b11001111111111011100100110000111001100011000001000000 A
b0 C
1&
#21500
0&
b1100 /
b11000011001000011110001111011010 -
b11000011001000011110001111011010 3
b10000000000000000000000000000001 ,
b10000000000000000000000000000001 2
b11000011001000011110001111011010 +
b11000011001000011110001111011010 1
b11000011001000011110001111011010 *
b10000000000000000000000000000001 )
b11000011001000011110001111011010 (
#21750
b1111111111111111111111111111111111110100110011010111000110101101 !
b1111111111111111111111111111111111110100110011010111000110101101 4
b1111111111111111111111111111111111110101110000101011001010110010 #
b1111111111111111111111111111111111110101110000101011001010110010 6
b1111111111111111111111111111111111110011101101001100110110010000 "
b1111111111111111111111111111111111110011101101001100110110010000 5
b100010 D
b1110111011100011011011011010000001101000011101110011111100100010 <
b1111101100000101101000111010011010110011111100011111000010011000 >
b1111001111111011100010111011100000101101010011101101100011100010 ;
b1000101010001100110001110000000011011000000010011110010 @
b1111110111000011011001100101101111111110010110011011000101011001 7
b1111011010111001010011100110110101110111101101101001100110100011 8
b1111110101000010001111010100101010110101100110000011111100111111 =
b1111110010100000000101011011100010011110011000001011001000110011 :
b1111111010000000000101011000110100110010100000111001100111111010 ?
b111110110100011110110011001011011100010100101000110000 A
b0 C
1&
#22000
0&
b1111 /
b10101100001110010001000011001010 -
b10101100001110010001000011001010 3
b11011010011000011011100111111000 ,
b11011010011000011011100111111000 2
b1100001110010001000011001000 +
b1100001110010001000011001000 1
b10101100001110010001000011001010 *
b11011010011000011011100111111000 )
b1100001110010001000011001000 (
#22250
b1111111111111111111111111111111111111110110100101100111110101000 !
b1111111111111111111111111111111111111110110100101100111110101000 4
b1111111111111111111111111111111111110110011110011011001111000111 #
b1111111111111111111111111111111111110110011110011011001111000111 6
b1111111111111111111111111111111111111000110010000101001000110101 "
b1111111111111111111111111111111111111000110010000101001000110101 5
b100010 D
b1111101000100000010011000000000111000001001100101101000010101111 <
b1111111010101010110000100111110011110100111001000010010111000010 >
b1111100011000100001100010010001001000000110101101100011010010111 ;
b1100111101001011100111110111110100111010000100000010010 @
b1001110101110101100010000111001001100011010000010011110 7
b1111101001101000001010010110100110000101001001000100000101110011 8
b1111111001011100000001111011100010111011101100101000010100100100 =
b1111110110111110101110011110101101100100100010111000011100111001 :
b1111110111000011011001100101101111111110010110011011000101011001 ?
b1000101010001100110001110000000011011000000010011110010 A
b0 C
1&
#22500
0&
b10010 /
b100101100111100100011000001000 -
b100101100111100100011000001000 3
b1010011110001101110111100110110 ,
b1010011110001101110111100110110 2
b0 +
b0 1
b100101100111100100011000001000 *
b1010011110001101110111100110110 )
b0 (
#22750
b10000100101010011100010110111 !
b10000100101010011100010110111 4
b100110101111010001100101000 #
b100110101111010001100101000 6
b1001011110100011001111001101 "
b1001011110100011001111001101 5
b100010 D
b1011010111101101100011000110010111011100111010111010111001010 <
b100110100001010001010110101111001110101100010110110000000010 >
b101010000001001010001110011010100011000011011000101110001010 ;
b101111011100111001101110110101101111111100000010101000110 @
b11011001001100110001101101100001000010100011100101011011111 7
b11110101001011111000101010111011100101011011110101001100111 8
b1011010111101011001001000011000110010111111010000100100011 =
b1010000100101111001001111110011011001101110100000001100100 :
b1001110101110101100010000111001001100011010000010011110 ?
b1100111101001011100111110111110100111010000100000010010 A
b0 C
1&
#23000
0&
b10101 /
b1111111111111111111111111111111 -
b1111111111111111111111111111111 3
b111100110111100001110000100110 ,
b111100110111100001110000100110 2
b11110011110001101110111100111000 +
b11110011110001101110111100111000 1
b1111111111111111111111111111111 *
b111100110111100001110000100110 )
b11110011110001101110111100111000 (
#23250
b10011110110000111010010001001 !
b10011110110000111010010001001 4
b10100010100000010000001001101 #
b10100010100000010000001001101 6
b1111100101101001100011011010 "
b1111100101101001100011011010 5
b100010 D
b10000111011010100010000101100001100100001100010011011011111111 <
b111100110100100001110000101100111001001101101001111110010101 >
b1001110001000001100111101111111101001010001010011010101110101 ;
b1010110010100010001001101000010000101110011001011110011011 @
b100111001101010100001001111101111100111111010010101101010101 7
b111000100000111111010111010000101101000010111100000100110101 8
b10101100111001101100110101110111100001110010111010001000000 =
b10011011010000101000010100101101010100111011100101110010110 :
b11011001001100110001101101100001000010100011100101011011111 ?
b101111011100111001101110110101101111111100000010101000110 A
b0 C
1&
#23500
0&
b11000 /
b100101100111100100011000001000 -
b100101100111100100011000001000 3
b11110011110001101110111100111000 ,
b11110011110001101110111100111000 2
b111100110111100001110000100110 +
b111100110111100001110000100110 1
b100101100111100100011000001000 *
b11110011110001101110111100111000 )
b111100110111100001110000100110 (
#23750
b1100100110011010010101110 !
b1100100110011010010101110 4
b1111011101001000011101001011 #
b1111011101001000011101001011 6
b1111111111111111111111111111111111111110001110110110110011101100 "
b1111111111111111111111111111111111111110001110110110110011101100 5
b100010 D
b10000001110111110101111110010000010110001111111111101010011 <
b110010000111000010111010011011111001101000101101011111001 >
b1100101010111101100011000010010000011101001001000101101101 ;
b10110010110000010000010101000110111011000001000110010010 @
b11010101101001011111010011011111001001110110001100111110 7
b1001101111101110101011000010010000011001111001100110110010 8
b10111011001110111000000000000000000011001111011110111011 =
b10011111011110111010000000111001000101110001110010001111 :
b100111001101010100001001111101111100111111010010101101010101 ?
b1010110010100010001001101000010000101110011001011110011011 A
b0 C
1&
#24000
0&
b11011 /
b10101100001110010001000011001010 -
b10101100001110010001000011001010 3
b0 ,
b0 2
b1010011110001101110111100110110 +
b1010011110001101110111100110110 1
b10101100001110010001000011001010 *
b0 )
b1010011110001101110111100110110 (
#24250
b1111111111111111111111111111111111101111111111001010001110111001 !
b1111111111111111111111111111111111101111111111001010001110111001 4
b1111111111111111111111111111111111111010010001101110100101110101 #
b1111111111111111111111111111111111111010010001101110100101110101 6
b1111111111111111111111111111111111110001011000011011111110111010 "
b1111111111111111111111111111111111110001011000011011111110111010 5
b100010 D
b1110000110100100001100001010010100101100000100110110110000111010 <
b1110110111011111101111010100010011001101110111011010001011011001 >
b1111000100000010001111111101011101000111001001001111001111001000 ;
b1111101110110101111101111101001101101100111010110101110000010001 @
b1111001101000001101011100001101011111010111110101101010011010011 7
b1111011001100100001100001010110101110100010000100010010111000010 8
b1111101010011110000011110010100111010010111000101100111000000110 =
b1111110100000000100011111100101100000000101010101011111111000100 :
b11010101101001011111010011011111001001110110001100111110 ?
b10110010110000010000010101000110111011000001000110010010 A
b0 C
1&
#24500
0&
b11110 /
b11000011001000011110001111011010 -
b11000011001000011110001111011010 3
b1100001110010001000011001000 ,
b1100001110010001000011001000 2
b11011010011000011011100111111000 +
b11011010011000011011100111111000 1
b11000011001000011110001111011010 *
b1100001110010001000011001000 )
b11011010011000011011100111111000 (
#24750
b1111111111111111111111111111111111101111100000001101010011010100 !
b1111111111111111111111111111111111101111100000001101010011010100 4
b1111111111111111111111111111111111101101111110011011101101000111 #
b1111111111111111111111111111111111101101111110011011101101000111 6
b1111111111111111111111111111111111111111000111111101100000001100 "
b1111111111111111111111111111111111111111000111111101100000001100 5
b100010 D
b1110011010010010000100110001011110110010110100000110101000001101 <
b1111000010100100101011100011111101000110010001100101010001111110 >
b1111011101000001000110111111110101011010010110011111100100010111 ;
b1111101100011011010001111101110000001111011011001000101100101111 @
b1111010000011010100111010111011110011100011011100111111000111000 7
b1111101010110111000010110011010110110000100000100010001011010001 8
b1111110010001010000100001100011110101001110101111101011001000110 =
b1111111101110001001001110101110000100111011101000011100111011011 :
b1111001101000001101011100001101011111010111110101101010011010011 ?
b1111101110110101111101111101001101101100111010110101110000010001 A
b0 C
1&
#25000
0&
b100001 /
b1100001110010001000011001000 -
b1100001110010001000011001000 3
b11000011001000011110001111011010 ,
b11000011001000011110001111011010 2
b10000000000000000000000000000001 +
b10000000000000000000000000000001 1
b1100001110010001000011001000 *
b11000011001000011110001111011010 )
b10000000000000000000000000000001 (
#25250
b1111111111111111111111111111111111111000101000110111001111111110 !
b1111111111111111111111111111111111111000101000110111001111111110 4
b1111111111111111111111111111111111110010000010101111011011000000 #
b1111111111111111111111111111111111110010000010101111011011000000 6
b1000101110101000001011011011 "
b1000101110101000001011011011 5
b100010 D
b1111111110110001010100000011111000000101110100111000010111010111 <
b11000010001000000011110101010100000011011000010010101011110 >
b110101110110010011100100001001000100010000010000000000110 ;
b111011001001100101100110111001011111111110001010001101000 @
b1111100000111001110011000010101000011101010110000110000100 7
b1111111101111110101011110000111001010000100100010101110000101100 8
b1000110000000110101011100111110111111101101100001111011010 =
b110001001011100010010011000100000100110011011110010 :
b1111010000011010100111010111011110011100011011100111111000111000 ?
b1111101100011011010001111101110000001111011011001000101100101111 A
b0 C
1&
#25500
0&
b100100 /
b0 -
b0 3
b10101100001110010001000011001010 ,
b10101100001110010001000011001010 2
b11011010011000011011100111111000 +
b11011010011000011011100111111000 1
b0 *
b10101100001110010001000011001010 )
b11011010011000011011100111111000 (
#25750
b110000011010001001111001000 !
b110000011010001001111001000 4
b1111111111111111111111111111111111111100100010000011011100000001 #
b1111111111111111111111111111111111111100100010000011011100000001 6
b1111111111111111111111111111111111111001100101111100011101111011 "
b1111111111111111111111111111111111111001100101111100011101111011 5
b100010 D
b100111100111100000100010100001111100101111101101001010001001 <
b110110001101010001101011101100111111010111111101001011100011 >
b1111110001101111010010011100100111011011010001101010111010011010 ;
b10111111011100100111100011011100000010000000000110110010011 @
b101111111111011110101001101011001101010010001000011110101111 7
b1111101011100001011111011010100101101001001011110110001101100110 8
b110001101110011000010000001110010000101110100101100110100 =
b1111110000111100011001110001111000000110111001011110111001011100 :
b1111100000111001110011000010101000011101010110000110000100 ?
b111011001001100101100110111001011111111110001010001101000 A
b0 C
1&
#26000
0&
b100111 /
b11110011110001101110111100111000 -
b11110011110001101110111100111000 3
b100101100111100100011000001000 ,
b100101100111100100011000001000 2
b1010011110001101110111100110110 +
b1010011110001101110111100110110 1
b11110011110001101110111100111000 *
b100101100111100100011000001000 )
b1010011110001101110111100110110 (
#26250
b10100100100101000101000011000 !
b10100100100101000101000011000 4
b1011011110101001000100100111 #
b1011011110101001000100100111 6
b1111111111111111111111111111111111111000101101010010111011011000 "
b1111111111111111111111111111111111111000101101010010111011011000 5
b100010 D
b1000011001001000010001101011001111110101110010011110001101010 <
b1111000001101000101111110000011000001001011100011010110100 >
b101100000111110010001011111111101110010010101110000110110 ;
b100011010001011011010101010101000000000110011010101110111 @
b10001110000001101101101011100011100011111000011000100100000 7
b1000001111100011001111001100000010000111111100011010100010 8
b1111111101010001011011000010010011111011101010011001010110010100 =
b1111111110111001011000011100000000001011111110111000111001111011 :
b101111111111011110101001101011001101010010001000011110101111 ?
b10111111011100100111100011011100000010000000000110110010011 A
b0 C
1&
#26500
0&
b101010 /
b111100110111100001110000100110 -
b111100110111100001110000100110 3
b1111111111111111111111111111111 ,
b1111111111111111111111111111111 2
b111100110111100001110000100110 +
b111100110111100001110000100110 1
b111100110111100001110000100110 *
b1111111111111111111111111111111 )
b111100110111100001110000100110 (
#26750
b1111101111100110001001001000 !
b1111101111100110001001001000 4
b10110001101001001100010110101 #
b10110001101001001100010110101 6
b10000010001101011101011010001 "
b10000010001101011101011010001 5
b100010 D
b1011110000111001101001101110001011110111111101111101101100100 <
b101111101011100010000101100110100101100001111011101000100 >
b1001111011001000010011101011010100011010100111000000001001000 ;
b1111110100100101011111110000101010000100011100010011101111100001 @
b1111111010100110001101010111011001101001101100000111110110110101 7
b1000100000001110011100100000111011000010100110000011010111001 8
b1011010111001110111001010011001011000000000111100110001111 =
b11111000100010000110010111001000111101110001101111011111001 :
b10001110000001101101101011100011100011111000011000100100000 ?
b100011010001011011010101010101000000000110011010101110111 A
b0 C
1&
#27000
0&
b101101 /
b1010011110001101110111100110110 -
b1010011110001101110111100110110 3
b100101100111100100011000001000 ,
b100101100111100100011000001000 2
b11110011110001101110111100111000 +
b11110011110001101110111100111000 1
b1010011110001101110111100110110 *
b100101100111100100011000001000 )
b11110011110001101110111100111000 (
#27250
b1111111111111111111111111111111111110101111101111000111001000100 !
b1111111111111111111111111111111111110101111101111000111001000100 4
b111111100000001110100101010 #
b111111100000001110100101010 6
b1010000101011011001010010110 "
b1010000101011011001010010110 5
b100010 D
b1111111100100000000110101001100100010001100000000100101011100110 <
b1001010101001111111000001100010101001011001100000110001010 >
b11110000000010011010000101010001000001011110100001001101001 ;
b10000011001100110110010111110100110111011101000111110 @
b1111111101111100101000101111011110110011010111001110010001010000 7
b10010100111101100000111111100100110010111110110010100101111 8
b1011011000100111001000101101100001110011111101110100111010 =
b1001110111010110000010100101001101010101100001101000110101 :
b1111111010100110001101010111011001101001101100000111110110110101 ?
b1111110100100101011111110000101010000100011100010011101111100001 A
b0 C
1&
#27500
0&
b110000 /
b11011010011000011011100111111000 -
b11011010011000011011100111111000 3
b10101100001110010001000011001010 ,
b10101100001110010001000011001010 2
b0 +
b0 1
b11011010011000011011100111111000 *
b10101100001110010001000011001010 )
b0 (
