ParallelFilter_L=3/filter.sv
`timescale 1ns / 1ps

module filter(
  input logic clk,
  input logic rst,
  input logic signed [31:0] x_in,
  input logic signed [31:0] x_in1,
  input logic signed [31:0] x_in2,
  output logic signed [63:0] y_out,
  output logic signed [63:0] y_out1,
  output logic signed [63:0] y_out2
);

parameter NUM_TAPS = 102;

logic signed [31:0] coeffs [102:0];

always_comb begin 
  coeffs[0] = 32'b11111111111110000010000011101100;
  coeffs[1] = 32'b11111111111000010011001010000001;
  coeffs[2] = 32'b11111111101011100010111001111001;
  coeffs[3] = 32'b11111111010011101111001000101101;
  coeffs[4] = 32'b11111110101101101111000110001010;
  coeffs[5] = 32'b11111101110111110111100010111000;
  coeffs[6] = 32'b11111100110100010100110110110111;
  coeffs[7] = 32'b11111011101001011101101101010111;
  coeffs[8] = 32'b11111010100010100111011001000011;
  coeffs[9] = 32'b11111001101101111111100111111111;
  coeffs[10] = 32'b11111001011010011101011111111110;
  coeffs[11] = 32'b11111001110010111111111101010011;
  coeffs[12] = 32'b11111010111011010101111011010111;
  coeffs[13] = 32'b11111100101100101101111001110001;
  coeffs[14] = 32'b11111110110110000001000110111110;
  coeffs[15] = 32'b00000000111110000010100110001000;
  coeffs[16] = 32'b00000010101001011010110110000000;
  coeffs[17] = 32'b00000011100001010010111010001011;
  coeffs[18] = 32'b00000011011010011010010100001110;
  coeffs[19] = 32'b00000010011000111100101011100000;
  coeffs[20] = 32'b00000000110000110111000110011101;
  coeffs[21] = 32'b11111111000000110111110001011111;
  coeffs[22] = 32'b11111101101010010011111101110010;
  coeffs[23] = 32'b11111101000110111111001100000111;
  coeffs[24] = 32'b11111101100001001011010110000110;
  coeffs[25] = 32'b11111110101111100111010001101110;
  coeffs[26] = 32'b00000000010111111110001101011110;
  coeffs[27] = 32'b00000001110110101110101010000111;
  coeffs[28] = 32'b00000010101010111010000001111100;
  coeffs[29] = 32'b00000010100001010010001000001011;
  coeffs[30] = 32'b00000001011011110110001011011000;
  coeffs[31] = 32'b11111111110010000001100101001000;
  coeffs[32] = 32'b11111110001001101010010111101101;
  coeffs[33] = 32'b11111101001010001001010011000111;
  coeffs[34] = 32'b11111101001110010001111000001100;
  coeffs[35] = 32'b11111110011001011000100000110110;
  coeffs[36] = 32'b00000000010100001011100010001100;
  coeffs[37] = 32'b00000010010010111000011111011011;
  coeffs[38] = 32'b00000011100011011111000110001011;
  coeffs[39] = 32'b00000011011111101001010101110110;
  coeffs[40] = 32'b00000001111100011111001111010010;
  coeffs[41] = 32'b11111111010010010111100110101101;
  coeffs[42] = 32'b11111100011001011001110000001110;
  coeffs[43] = 32'b11111010011010101010011011100011;
  coeffs[44] = 32'b11111010011010001100111111001111;
  coeffs[45] = 32'b11111101000000010110011101000010;
  coeffs[46] = 32'b00000010001001101111111101000100;
  coeffs[47] = 32'b00001001000011100100110011010111;
  coeffs[48] = 32'b00010000010110000000010110001000;
  coeffs[49] = 32'b00010110011010010110100111011111;
  coeffs[50] = 32'b00011001110110101011101000100111;
  coeffs[51] = 32'b00011001110110101011101000100111;
  coeffs[52] = 32'b00010110011010010110100111011111;
  coeffs[53] = 32'b00010000010110000000010110001000;
  coeffs[54] = 32'b00001001000011100100110011010111;
  coeffs[55] = 32'b00000010001001101111111101000100;
  coeffs[56] = 32'b11111101000000010110011101000010;
  coeffs[57] = 32'b11111010011010001100111111001111;
  coeffs[58] = 32'b11111010011010101010011011100011;
  coeffs[59] = 32'b11111100011001011001110000001110;
  coeffs[60] = 32'b11111111010010010111100110101101;
  coeffs[61] = 32'b00000001111100011111001111010010;
  coeffs[62] = 32'b00000011011111101001010101110110;
  coeffs[63] = 32'b00000011100011011111000110001011;
  coeffs[64] = 32'b00000010010010111000011111011011;
  coeffs[65] = 32'b00000000010100001011100010001100;
  coeffs[66] = 32'b11111110011001011000100000110110;
  coeffs[67] = 32'b11111101001110010001111000001100;
  coeffs[68] = 32'b11111101001010001001010011000111;
  coeffs[69] = 32'b11111110001001101010010111101101;
  coeffs[70] = 32'b11111111110010000001100101001000;
  coeffs[71] = 32'b00000001011011110110001011011000;
  coeffs[72] = 32'b00000010100001010010001000001011;
  coeffs[73] = 32'b00000010101010111010000001111100;
  coeffs[74] = 32'b00000001110110101110101010000111;
  coeffs[75] = 32'b00000000010111111110001101011110;
  coeffs[76] = 32'b11111110101111100111010001101110;
  coeffs[77] = 32'b11111101100001001011010110000110;
  coeffs[78] = 32'b11111101000110111111001100000111;
  coeffs[79] = 32'b11111101101010010011111101110010;
  coeffs[80] = 32'b11111111000000110111110001011111;
  coeffs[81] = 32'b00000000110000110111000110011101;
  coeffs[82] = 32'b00000010011000111100101011100000;
  coeffs[83] = 32'b00000011011010011010010100001110;
  coeffs[84] = 32'b00000011100001010010111010001011;
  coeffs[85] = 32'b00000010101001011010110110000000;
  coeffs[86] = 32'b00000000111110000010100110001000;
  coeffs[87] = 32'b11111110110110000001000110111110;
  coeffs[88] = 32'b11111100101100101101111001110001;
  coeffs[89] = 32'b11111010111011010101111011010111;
  coeffs[90] = 32'b11111001110010111111111101010011;
  coeffs[91] = 32'b11111001011010011101011111111110;
  coeffs[92] = 32'b11111001101101111111100111111111;
  coeffs[93] = 32'b11111010100010100111011001000011;
  coeffs[94] = 32'b11111011101001011101101101010111;
  coeffs[95] = 32'b11111100110100010100110110110111;
  coeffs[96] = 32'b11111101110111110111100010111000;
  coeffs[97] = 32'b11111110101101101111000110001010;
  coeffs[98] = 32'b11111111010011101111001000101101;
  coeffs[99] = 32'b11111111101011100010111001111001;
  coeffs[100] = 32'b11111111111000010011001010000001;
  coeffs[101] = 32'b11111111111110000010000011101100;
end

// Instantiate sample registers
logic signed [31:0] x_3k_samples [(NUM_TAPS / 3) - 1:0];
logic signed [31:0] x_3k1_samples [(NUM_TAPS / 3) - 1:0];
logic signed [31:0] x_3k2_samples [(NUM_TAPS / 3) - 1:0];

// Initialize intermediate computations to be accessed by various function units
// in the filter
logic signed [63:0] h0, h1, h2, h01, h12, h012, h2_delay, h12minh1_delay;  
logic signed [63:0] h01minh1, h12minh1; 

// Instantiate adders for intermediate computations
assign h12minh1 = h12 - h1;
assign h01minh1 = h01 - h1;

always_ff @(posedge clk or posedge rst) begin
  if (rst) begin
    // Clear the delay units
    h2_delay <= 0;
    h12minh1_delay <= 0;
    for (int i=0; i < NUM_TAPS/3-1; i=i+1) begin
      // Clear the sample registers
      x_3k_samples[i] <= 0;
      x_3k1_samples[i] <= 0;
      x_3k2_samples[i] <= 0;
    end 
  end else begin
    for (int i=NUM_TAPS/2-1; i > 0; i=i-1) begin
      // Shift samples
      x_3k_samples[i] <= x_3k_samples[i-1];
      x_3k1_samples[i] <= x_3k1_samples[i-1];
      x_3k2_samples[i] <= x_3k2_samples[i-1];
    end
    // Take in new samples
    x_3k_samples[0] <= x_in;
    x_3k1_samples[0] <= x_in1;
    x_3k2_samples[0] <= x_in2;

    // push delay signals through their delay units
    h2_delay <= h2;
    h12minh1_delay <= h12minh1;
  end
end

always_comb begin
  h0 = 0;
  h1 = 0;
  h2 = 0;
  h01 = 0;
  h12 = 0;
  h012 = 0;
  
  for (int i=0; i <= (NUM_TAPS/3) - 1; i=i+1) begin
    // Perform multiplication with coefficients and accumulations in all three
    // paths
    h0 += x_3k_samples[i] * coeffs[3*i];
    h1 += x_3k1_samples[i] * coeffs[3*i+1];
    h2 += x_3k2_samples[i] * coeffs[3*i+2];

    h01 += (x_3k_samples[i] + x_3k1_samples[i]) * (coeffs[3*i] + coeffs[3*i+1]); 
    h12 += (x_3k1_samples[i] + x_3k2_samples[i]) * (coeffs[3*i+1] + coeffs[3*i+2]); 
    h012 += (x_3k_samples[i] + x_3k1_samples[i] + x_3k2_samples[i]) * (coeffs[3*i] + coeffs[3*i+1] + coeffs[3*i+2]); 
  end
end

// Perform final summations and output the filtered data
assign y_out = (h0 - h2_delay + h12minh1_delay) >>> 31;
assign y_out1 = (h01minh1 - h0 - h2_delay) >>> 31;
assign y_out2 = (h012 - h01minh1 - h12minh1) >>> 31;

endmodule

ParallelFilter_L=3/filter_tb.sv
`timescale 1ns / 1ps

module filter_tb;

  logic clk;
  logic rst;
  logic signed [31:0] x_in, x_in1, x_in2;
  logic signed [63:0] y_out, y_out1, y_out2;

  parameter CLK_PERIOD = 0.5; // 2GHz Clock
  parameter NUM_SAMPLES = 1000;

  filter uut(
    .clk(clk),
    .rst(rst),
    .x_in(x_in),
    .x_in1(x_in1),
    .x_in2(x_in2),
    .y_out(y_out),
    .y_out1(y_out1),
    .y_out2(y_out2)
  );


  // Start the clock
  initial begin
    clk = 0;
    forever #(CLK_PERIOD / 2) clk = ~clk;
  end

  integer file, status;
  integer sample_count;

  logic signed [31:0] sample_data, sample_data1, sample_data2;

  initial begin
    $dumpfile("filter_tb.vcd");
    $dumpvars(0, filter_tb);

    rst = 1;
    x_in = 0;
    sample_count = 0;

    // Open the raw signal data
    file = $fopen("../Python/InputSignals/cosine_wave_100MHz_500MHz.bin", "rb");
    if (file == 0) begin
        $display("Error: Unable to open file!");
        $finish;
    end

    #20 rst = 0;

    // Read and feed samples to the pipeline
    while (sample_count < NUM_SAMPLES) begin
      status = $fread(sample_data, file);
      if (status == 0) begin
        $display("Error: End of file reached or read error!");
        $finish;
      end
      
      status = $fread(sample_data1, file);
      if (status == 0) begin
        $display("Error: End of file reached or read error!");
        $finish;
      end
      
      status = $fread(sample_data2, file);
      if (status == 0) begin
        $display("Error: End of file reached or read error!");
        $finish;
      end

      x_in = sample_data;
      x_in1 = sample_data1;
      x_in2 = sample_data2;
      sample_count = sample_count + 3;
      #CLK_PERIOD;
    end

    $fclose(file);
    #100 $finish;
  end

endmodule

ParallelFilter_L=3/filter_tb.vcd
$date
	Tue Mar 18 18:50:04 2025
$end
$version
	Icarus Verilog
$end
$timescale
	1ps
$end
$scope module filter_tb $end
$var wire 64 ! y_out2 [63:0] $end
$var wire 64 " y_out1 [63:0] $end
$var wire 64 # y_out [63:0] $end
$var real 1 $ CLK_PERIOD $end
$var parameter 32 % NUM_SAMPLES $end
$var reg 1 & clk $end
$var reg 1 ' rst $end
$var reg 32 ( sample_data [31:0] $end
$var reg 32 ) sample_data1 [31:0] $end
$var reg 32 * sample_data2 [31:0] $end
$var reg 32 + x_in [31:0] $end
$var reg 32 , x_in1 [31:0] $end
$var reg 32 - x_in2 [31:0] $end
$var integer 32 . file [31:0] $end
$var integer 32 / sample_count [31:0] $end
$var integer 32 0 status [31:0] $end
$scope module uut $end
$var wire 1 & clk $end
$var wire 1 ' rst $end
$var wire 32 1 x_in [31:0] $end
$var wire 32 2 x_in1 [31:0] $end
$var wire 32 3 x_in2 [31:0] $end
$var wire 64 4 y_out2 [63:0] $end
$var wire 64 5 y_out1 [63:0] $end
$var wire 64 6 y_out [63:0] $end
$var wire 64 7 h12minh1 [63:0] $end
$var wire 64 8 h01minh1 [63:0] $end
$var parameter 32 9 NUM_TAPS $end
$var reg 64 : h0 [63:0] $end
$var reg 64 ; h01 [63:0] $end
$var reg 64 < h012 [63:0] $end
$var reg 64 = h1 [63:0] $end
$var reg 64 > h12 [63:0] $end
$var reg 64 ? h12minh1_delay [63:0] $end
$var reg 64 @ h2 [63:0] $end
$var reg 64 A h2_delay [63:0] $end
$scope begin $ivl_for_loop0 $end
$var integer 32 B i [31:0] $end
$upscope $end
$scope begin $ivl_for_loop1 $end
$var integer 32 C i [31:0] $end
$upscope $end
$scope begin $ivl_for_loop2 $end
$var integer 32 D i [31:0] $end
$upscope $end
$upscope $end
$upscope $end
$enddefinitions $end
$comment Show the parameter values. $end
$dumpall
b1100110 9
b1111101000 %
r0.5 $
$end
#0
$dumpvars
b100010 D
b0 C
b100001 B
b0 A
bx @
b0 ?
bx >
bx =
bx <
bx ;
bx :
bx 8
bx 7
bx 6
bx 5
bx 4
bx 3
bx 2
b0 1
bx 0
b0 /
b10000000000000000000000000000011 .
bx -
bx ,
b0 +
bx *
bx )
bx (
1'
0&
bx #
bx "
bx !
$end
#250
b100001 B
1&
#500
0&
#750
b100001 B
1&
#1000
0&
#1250
b100001 B
1&
#1500
0&
#1750
b100001 B
1&
#2000
0&
#2250
b100001 B
1&
#2500
0&
#2750
b100001 B
1&
#3000
0&
#3250
b100001 B
1&
#3500
0&
#3750
b100001 B
1&
#4000
0&
#4250
b100001 B
1&
#4500
0&
#4750
b100001 B
1&
#5000
0&
#5250
b100001 B
1&
#5500
0&
#5750
b100001 B
1&
#6000
0&
#6250
b100001 B
1&
#6500
0&
#6750
b100001 B
1&
#7000
0&
#7250
b100001 B
1&
#7500
0&
#7750
b100001 B
1&
#8000
0&
#8250
b100001 B
1&
#8500
0&
#8750
b100001 B
1&
#9000
0&
#9250
b100001 B
1&
#9500
0&
#9750
b100001 B
1&
#10000
0&
#10250
b100001 B
1&
#10500
0&
#10750
b100001 B
1&
#11000
0&
#11250
b100001 B
1&
#11500
0&
#11750
b100001 B
1&
#12000
0&
#12250
b100001 B
1&
#12500
0&
#12750
b100001 B
1&
#13000
0&
#13250
b100001 B
1&
#13500
0&
#13750
b100001 B
1&
#14000
0&
#14250
b100001 B
1&
#14500
0&
#14750
b100001 B
1&
#15000
0&
#15250
b100001 B
1&
#15500
0&
#15750
b100001 B
1&
#16000
0&
#16250
b100001 B
1&
#16500
0&
#16750
b100001 B
1&
#17000
0&
#17250
b100001 B
1&
#17500
0&
#17750
b100001 B
1&
#18000
0&
#18250
b100001 B
1&
#18500
0&
#18750
b100001 B
1&
#19000
0&
#19250
b100001 B
1&
#19500
0&
#19750
b100001 B
1&
#20000
0&
b11 /
b1100111100011011101111001101101 -
b1100111100011011101111001101101 3
b1111001101111000011100001001100 ,
b1111001101111000011100001001100 2
b1111111111111111111111111111111 +
b1111111111111111111111111111111 1
b1100111100011011101111001101101 *
b1111001101111000011100001001100 )
b100 0
b1111111111111111111111111111111 (
0'
#20250
b1111111111111111111111111111111111111111100010101000010010110000 !
b1111111111111111111111111111111111111111100010101000010010110000 4
b100010 D
b1111111101011001101101110011111100000001000010110010000101010000 <
b1111111110101011100010010110101001111001100100110101101001011110 7
b1111111110011100111000111010001111000011001101101001000010101010 >
b1111111111101000111010110111110001111110010101000001001010100011 8
b1111111111011010010001011011010111000111111101110100100011101111 ;
b1111111111011110111001110101101100110001000110111011011110000101 @
b1111111111110001010110100011100101001001101000110011011001001100 =
b1111111111111100000100000111011000000000000001111101111100010100 :
bx ?
bx A
b0 C
1&
#20500
0&
b110 /
b0 -
b0 3
b100111100011011101111001101110 ,
b100111100011011101111001101110 2
b1001011001111001000110000010001 +
b1001011001111001000110000010001 1
b0 *
b100111100011011101111001101110 )
b1001011001111001000110000010001 (
#20750
b1111111111111111111111111111111111111011110111011010101110011000 !
b1111111111111111111111111111111111111011110111011010101110011000 4
b1111111111111111111111111111111111111110111000111001010111011100 #
b1111111111111111111111111111111111111110111000111001010111011100 6
b1111111111111111111111111111111111111110001111000011010110111100 "
b1111111111111111111111111111111111111110001111000011010110111100 5
b100010 D
b1111101000100000000011001111011101010101011000001010011011100010 <
b1111110011101101110011111110110111010100010011101110110100011110 >
b1111111000000000111011101111001100110110010010110100001110110000 ;
b1111111100100011101110111100111001101000001011011111011001011000 @
b1111110110001111000011000001001011100001001101000111011010111000 7
b1111111010100010001010110001100001000011001100001100110101001010 8
b1111111101011110110000111101101011110011000110100111011001100110 =
b1111111110100101001010001101111100001101011111000100110101111111 :
b1111111110101011100010010110101001111001100100110101101001011110 ?
b1111111111011110111001110101101100110001000110111011011110000101 A
b0 C
1&
#21000
0&
b1001 /
b10011000011100100010000110010011 -
b10011000011100100010000110010011 3
b10110100110000110111001111101111 ,
b10110100110000110111001111101111 2
b11011000011100100010000110010010 +
b11011000011100100010000110010010 1
b10011000011100100010000110010011 *
b10110100110000110111001111101111 )
b11011000011100100010000110010010 (
#21250
b1111111111111111111111111111111111110010010111111100000010100011 !
b1111111111111111111111111111111111110010010111111100000010100011 4
b1111111111111111111111111111111111111001010000100100101100010111 #
b1111111111111111111111111111111111111001010000100100101100010111 6
b1111111111111111111111111111111111111001011011011001010111010001 "
b1111111111111111111111111111111111111001011011011001010111010001 5
b100010 D
b1110110010100001001000110101111010100111011001011101100101000001 <
b1111011100100101010011101000000100001101100101011101100110011010 >
b1111011111010100110000110111000011111010011010100100111111010000 ;
b1111110111101011110001111011111010100110010011011011110100000010 @
b1111100101100000111001110000111001111101001101010010010100001011 7
b1111101000010000010110111111111001101010000010011001101101000001 8
b1111110111000100011001110111001010010000011000001011010010001111 =
b1111111000110101110101010100011101010110010000101001010111011110 :
b1111110110001111000011000001001011100001001101000111011010111000 ?
b1111111100100011101110111100111001101000001011011111011001011000 A
b0 C
1&
#21500
0&
b1100 /
b10000110010000111100011110110100 -
b10000110010000111100011110110100 3
b10000000000000000000000000000001 ,
b10000000000000000000000000000001 2
b10000110010000111100011110110100 +
b10000110010000111100011110110100 1
b10000110010000111100011110110100 *
b10000000000000000000000000000001 )
b10000110010000111100011110110100 (
#21750
b1111111111111111111111111111111111101100010100101011101110111100 !
b1111111111111111111111111111111111101100010100101011101110111100 4
b1111111111111111111111111111111111101111000000011000110110110000 #
b1111111111111111111111111111111111101111000000011000110110110000 6
b1111111111111111111111111111111111110101000000010100000000010110 "
b1111111111111111111111111111111111110101000000010100000000010110 5
b100010 D
b1110010000001001110011001000101101010000100100000011011110110001 <
b1111011000001010100001011000010011110100010000000111000111111011 >
b1111000100011010001101010111110010111101001110100000000001011001 ;
b1111111010000000110100000001010010001101000100100111011000010011 @
b1111100101101000010111110101101010010000010111000110000011011010 7
b1111010001111000000011110101001001011001010101011110111100111000 8
b1111110010100010001001100010101001100011111001000001000100100001 =
b1111110000001011101001111000100000110100101011001100011111000010 :
b1111100101100000111001110000111001111101001101010010010100001011 ?
b1111110111101011110001111011111010100110010011011011110100000010 A
b0 C
1&
#22000
0&
b1111 /
b11011000011100100010000110010010 -
b11011000011100100010000110010010 3
b10110100110000110111001111101111 ,
b10110100110000110111001111101111 2
b10011000011100100010000110010011 +
b10011000011100100010000110010011 1
b11011000011100100010000110010010 *
b10110100110000110111001111101111 )
b10011000011100100010000110010011 (
#22250
b1111111111111111111111111111111111111101000010110010000011110100 !
b1111111111111111111111111111111111111101000010110010000011110100 4
b1111111111111111111111111111111111101110101101011101010000101101 #
b1111111111111111111111111111111111101110101101011101010000101101 6
b1111111111111111111111111111111111111010010011001110000001100010 "
b1111111111111111111111111111111111111010010011001110000001100010 5
b100010 D
b1111101110111100010111011001001011100000010110010001101011010011 <
b10001111010110011100011100111001110101011110011111110011101 >
b1111011101111001001101110100110111101010111110101000100001100110 ;
b1011001101001100001001100101110000111101001110000011000001 @
b10100011100001100100000001001011110101101001000010010111011 7
b1111100000011010100110110001011001111010111111111100110110000100 8
b1111111101011110100111000011011101101111111110101011101011100010 =
b1111110001110011010110101101000011000100000000100010111010011110 :
b1111100101101000010111110101101010010000010111000110000011011010 ?
b1111111010000000110100000001010010001101000100100111011000010011 A
b0 C
1&
#22500
0&
b10010 /
b1001011001111001000110000010001 -
b1001011001111001000110000010001 3
b100111100011011101111001101110 ,
b100111100011011101111001101110 2
b0 +
b0 1
b1001011001111001000110000010001 *
b100111100011011101111001101110 )
b0 (
#22750
b11111001100101011010110011010 !
b11111001100101011010110011010 4
b1000001000011101001110011010 #
b1000001000011101001110011010 6
b1000111100011010010010001110 "
b1000111100011010010010001110 5
b100010 D
b10101111111100010010100100101111010111111100101011001111100001 <
b1100010010011010000101000110111111011000111100110010101110001 >
b111001000000001010011001100011011010011110110111010100110111 ;
b11011000011100011011011001101000010101111111011100111101101 @
b1001101011011000001000011100111101000111111011010011000100110 7
b100100000111111010110100010011001000010110101011010111101100 8
b10100111000001111100101010000010010001000001011111101001011 =
b111000001111010000110010000111100110100001110101110110000 :
b10100011100001100100000001001011110101101001000010010111011 ?
b1011001101001100001001100101110000111101001110000011000001 A
b0 C
1&
#23000
0&
b10101 /
b1111111111111111111111111111111 -
b1111111111111111111111111111111 3
b1111001101111000011100001001100 ,
b1111001101111000011100001001100 2
b1100111100011011101111001101101 +
b1100111100011011101111001101101 1
b1111111111111111111111111111111 *
b1111001101111000011100001001100 )
b1100111100011011101111001101101 (
#23250
b101000010010111110110101011111 !
b101000010010111110110101011111 4
b100111010000011100101010110001 #
b100111010000011100101010110001 6
b1111100011111101001011001001 "
b1111100011111101001011001001 5
b100010 D
b11100010100111110010000101011111011000010111001111101111010010 <
b1010111000001111101010000111110001011111011101111010111001000 >
b1110001101001111011110011101101110110100111001111010101011110 ;
b1111001000111001010000100010100100001010011100101001000100 @
b111011101100111010111011111000000010100001010110000011111010 7
b1010110010100111001011110100111101101001100110110000010010000 8
b11011010101000010010101000110001001011010011001010011001110 =
b11100001001011011101101000111011010010011100010111001110101 :
b1001101011011000001000011100111101000111111011010011000100110 ?
b11011000011100011011011001101000010101111111011100111101101 A
b0 C
1&
#23500
0&
b11000 /
b1001011001111001000110000010001 -
b1001011001111001000110000010001 3
b1100111100011011101111001101101 ,
b1100111100011011101111001101101 2
b1111001101111000011100001001100 +
b1111001101111000011100001001100 1
b1001011001111001000110000010001 *
b1100111100011011101111001101101 )
b1111001101111000011100001001100 (
#23750
b100101000011110001110101001 !
b100101000011110001110101001 4
b100000010100011010000101000010 #
b100000010100011010000101000010 6
b100101000110100011011001000 "
b100101000110100011011001000 5
b100010 D
b11001010100100111100000000100010001011001000001011111011010 <
b1111100110100000000001100011000101101011100110010111011010010001 >
b101111011010111111101011011000001010000110001011110010111111 ;
b1111110000100111001001111001011000100101100100111111010001111110 @
b1111100011100100010110011101001111100111110100100011011000011111 7
b101100011111010100100101100010000110010100010111110001001101 8
b10111011101011000101110110000011110001110100000001110010 =
b10100000100110010011110101111100001111001100001111011110001 :
b111011101100111010111011111000000010100001010110000011111010 ?
b1111001000111001010000100010100100001010011100101001000100 A
b0 C
1&
#24000
0&
b11011 /
b11011000011100100010000110010010 -
b11011000011100100010000110010010 3
b0 ,
b0 2
b100111100011011101111001101110 +
b100111100011011101111001101110 1
b11011000011100100010000110010010 *
b0 )
b100111100011011101111001101110 (
#24250
b1111111111111111111111111111111111011110110110011101010111011100 !
b1111111111111111111111111111111111011110110110011101010111011100 4
b1111111111111111111111111111111111110101010011010110000100100011 #
b1111111111111111111111111111111111110101010011010110000100100011 6
b1111111111111111111111111111111111110111100000101111101010001011 "
b1111111111111111111111111111111111110111100000101111101010001011 5
b100010 D
b1101000101110001010100100011011100101110000100110100000100110101 <
b1110011010010011001001100011100111111000111100111011000010110111 >
b1111000000110011000001010101000001011101010011001011110100111010 ;
b1111100100111000000011011000000101010000001010101101000010111111 @
b1110110000110010010001000001100101100010111010010001000100111010 7
b1111010111010010001000110010111111000111010000100001110110111101 8
b1111101001100000111000100010000010010110000010101001111101111101 =
b1111110111101001011111100101001111110001010011101101110010001001 :
b1111100011100100010110011101001111100111110100100011011000011111 ?
b1111110000100111001001111001011000100101100100111111010001111110 A
b0 C
1&
#24500
0&
b11110 /
b10000110010000111100011110110100 -
b10000110010000111100011110110100 3
b10011000011100100010000110010011 ,
b10011000011100100010000110010011 2
b10110100110000110111001111101111 +
b10110100110000110111001111101111 1
b10000110010000111100011110110100 *
b10011000011100100010000110010011 )
b10110100110000110111001111101111 (
#24750
b1111111111111111111111111111111111011110000111011000001101101010 !
b1111111111111111111111111111111111011110000111011000001101101010 4
b1111111111111111111111111111111111011010010100100111101011000010 #
b1111111111111111111111111111111111011010010100100111101011000010 6
b1111111111111111111111111111111111110101100000110000100111001001 "
b1111111111111111111111111111111111110101100000110000100111001001 5
b100010 D
b1101000010011011111101110111111001101001011110101101000000000101 <
b1110110111010100010011101001010001011010000100001111100001100111 >
b1110100010011000010010110010101001100001100111111111110101110011 ;
b1111110010110111011110110011000111111111000000101100001000100000 @
b1111001101100100100111001001100110000101011111110101100001110001 7
b1110111000101000100110010010111110001101000011100101110101111101 8
b1111101001101111101100011111101011010100100100011001111111110110 =
b1111101000101111000001101100100101100100101001110110110100001110 :
b1110110000110010010001000001100101100010111010010001000100111010 ?
b1111100100111000000011011000000101010000001010101101000010111111 A
b0 C
1&
#25000
0&
b100001 /
b10011000011100100010000110010011 -
b10011000011100100010000110010011 3
b10000110010000111100011110110100 ,
b10000110010000111100011110110100 2
b10000000000000000000000000000001 +
b10000000000000000000000000000001 1
b10011000011100100010000110010011 *
b10000110010000111100011110110100 )
b10000000000000000000000000000001 (
#25250
b1111111111111111111111111111111111110011000000110111011000000010 !
b1111111111111111111111111111111111110011000000110111011000000010 4
b1111111111111111111111111111111111100100001100101011100110001101 #
b1111111111111111111111111111111111100100001100101011100110001101 6
b1111111111111111111111111111111111111000100011010110010011000110 "
b1111111111111111111111111111111111111000100011010110010011000110 5
b100010 D
b1110110110110011110110010000100001101101101110111010110010011101 <
b1111110110101101010101100111101111111011000111111110111000000001 >
b1111001001010000000010100101110101101110000101100100100111000010 ;
b11111001100110101011011110100011010000011101110001101010 @
b1111111111000111101101010001001011101111011100111111110001110001 7
b1111010001101010011010001111010001100010011010100101100000110010 8
b1111110111100101101000010110100100001011101010111111000110010000 =
b1111101101101100001110110101111101001101000101100000101100110001 :
b1111001101100100100111001001100110000101011111110101100001110001 ?
b1111110010110111011110110011000111111111000000101100001000100000 A
b0 C
1&
#25500
0&
b100100 /
b0 -
b0 3
b11011000011100100010000110010010 ,
b11011000011100100010000110010010 2
b10110100110000110111001111101111 +
b10110100110000110111001111101111 1
b0 *
b11011000011100100010000110010010 )
b10110100110000110111001111101111 (
#25750
b1011111110010100000100011001 !
b1011111110010100000100011001 4
b1111111111111111111111111111111111111010110010111100110001000101 #
b1111111111111111111111111111111111111010110010111100110001000101 6
b1111111111111111111111111111111111111111000111010000111001110100 "
b1111111111111111111111111111111111111111000111010000111001110100 5
b100010 D
b1000010101000001000011111101110000001000110011111010100010010 <
b110101100111100011101110011100101110000010010011101101100011 >
b11111011111010001110101010010111100110001110110000010000 ;
b10010101001000000000010111011011011110011100001111111111111 @
b101110001011100100111011010111000111011111111001111101010111 7
b1111111100011111111011011011100100110001000011110101000000000100 8
b111011011111110110011000101100110100010011001110000001100 =
b1111111010010111110010111100011101111010001001111000101011111100 :
b1111111111000111101101010001001011101111011100111111110001110001 ?
b11111001100110101011011110100011010000011101110001101010 A
b0 C
1&
#26000
0&
b100111 /
b1100111100011011101111001101101 -
b1100111100011011101111001101101 3
b1001011001111001000110000010001 ,
b1001011001111001000110000010001 2
b100111100011011101111001101110 +
b100111100011011101111001101110 1
b1100111100011011101111001101101 *
b1001011001111001000110000010001 )
b100111100011011101111001101110 (
#26250
b100110111100100010111100100000 !
b100110111100100010111100100000 4
b10101100110100001010111010101 #
b10101100110100001010111010101 6
b1100011110000101100111001000 "
b1100011110000101100111001000 5
b100010 D
b11011011011101001110111001101111110010100010010010001100111110 <
b1101100010101010111001110001101000011010000000100000111110110 >
b1010101010000100000011100011000011101010011000100110100101111 ;
b11010110100000111101111111010110011010110100000100001101001 @
b1010010010100011111111001010001110000100110101011101100011101 7
b111011001111101001000111011101001010101001101100011001010110 8
b11010000000110111010100111011010010101001011000011011011001 =
b1111101010011101110110010000000000110101011001101110100100 :
b101110001011100100111011010111000111011111111001111101010111 ?
b10010101001000000000010111011011011110011100001111111111111 A
b0 C
1&
#26500
0&
b101010 /
b1111001101111000011100001001100 -
b1111001101111000011100001001100 3
b1111111111111111111111111111111 ,
b1111111111111111111111111111111 2
b1111001101111000011100001001100 +
b1111001101111000011100001001100 1
b1111001101111000011100001001100 *
b1111111111111111111111111111111 )
b1111001101111000011100001001100 (
#26750
b100001100001110011111011110110 !
b100001100001110011111011110110 4
b101011000101010011110101010111 #
b101011000101010011110101010111 6
b1110110011110101100000111100 "
b1110110011110101100000111100 5
b100010 D
b10111100100000001100110001010100101010001011110101000001110110 <
b111001011110110110101011001000100110110111110010011100100000 >
b1101110001110010110010111111011110001100101000111011100110000 ;
b100111101111000100100101001101100001001101101111000000100 @
b100010010110100010100110011010011000001111010110101100110000 7
b1010111000110000010010011001101100010111100101011101101000000 8
b10111001000010100000100101110001110101000011011101111110000 =
b11110101010001111100001011000110000100011011011110110111011 :
b1010010010100011111111001010001110000100110101011101100011101 ?
b11010110100000111101111111010110011010110100000100001101001 A
b0 C
1&
#27000
0&
b101101 /
b100111100011011101111001101110 -
b100111100011011101111001101110 3
b1001011001111001000110000010001 ,
b1001011001111001000110000010001 2
b1100111100011011101111001101101 +
b1100111100011011101111001101101 1
b100111100011011101111001101110 *
b1001011001111001000110000010001 )
b1100111100011011101111001101101 (
#27250
b1111111111111111111111111111111111101110001011001101101000000110 !
b1111111111111111111111111111111111101110001011001101101000000110 4
b10011001110011010110100000111 #
b10011001110011010110100000111 6
b1111111111111111111111111111111111111011111010101011001100001110 "
b1111111111111111111111111111111111111011111010101011001100001110 5
b100010 D
b1110011010011000000010011100100010101110100100110101111010101001 <
b1110101011100100011011001011010010100101000011110110101001100100 >
b1111111001010001101001000110001001011111011111111101111100111110 ;
b1111100011010101011100010001011110100111000110001101001001101111 @
b1110111000001010001100101000101111000001001000011010110011110011 7
b101110111011010100011100101111011100100100010000111001101 8
b1111110011011010001110100010100011100011111011011011110101110001 =
b1001000100001011100110011110110000100111101111110100110100 :
b100010010110100010100110011010011000001111010110101100110000 ?
b100111101111000100100101001101100001001101101111000000100 A
b0 C
1&
#27500
0&
b110000 /
b10110100110000110111001111101111 -
b10110100110000110111001111101111 3
b11011000011100100010000110010010 ,
b11011000011100100010000110010010 2
b0 +
b0 1
b10110100110000110111001111101111 *
b11011000011100100010000110010010 )
b0 (
