PipelinedParallelFilter_L=3/filter.sv
`timescale 1ns / 1ps

module filter(
  input logic clk,
  input logic rst,
  input logic signed [31:0] x_in,
  input logic signed [31:0] x_in1,
  input logic signed [31:0] x_in2,
  output logic signed [63:0] y_out,
  output logic signed [63:0] y_out1,
  output logic signed [63:0] y_out2

);


parameter NUM_TAPS = 102;

// Coefficients
logic signed [31:0] coeffs [102:0];

always_comb begin 
  coeffs[0] = 32'b11111111111110000010000011101100;
  coeffs[1] = 32'b11111111111000010011001010000001;
  coeffs[2] = 32'b11111111101011100010111001111001;
  coeffs[3] = 32'b11111111010011101111001000101101;
  coeffs[4] = 32'b11111110101101101111000110001010;
  coeffs[5] = 32'b11111101110111110111100010111000;
  coeffs[6] = 32'b11111100110100010100110110110111;
  coeffs[7] = 32'b11111011101001011101101101010111;
  coeffs[8] = 32'b11111010100010100111011001000011;
  coeffs[9] = 32'b11111001101101111111100111111111;
  coeffs[10] = 32'b11111001011010011101011111111110;
  coeffs[11] = 32'b11111001110010111111111101010011;
  coeffs[12] = 32'b11111010111011010101111011010111;
  coeffs[13] = 32'b11111100101100101101111001110001;
  coeffs[14] = 32'b11111110110110000001000110111110;
  coeffs[15] = 32'b00000000111110000010100110001000;
  coeffs[16] = 32'b00000010101001011010110110000000;
  coeffs[17] = 32'b00000011100001010010111010001011;
  coeffs[18] = 32'b00000011011010011010010100001110;
  coeffs[19] = 32'b00000010011000111100101011100000;
  coeffs[20] = 32'b00000000110000110111000110011101;
  coeffs[21] = 32'b11111111000000110111110001011111;
  coeffs[22] = 32'b11111101101010010011111101110010;
  coeffs[23] = 32'b11111101000110111111001100000111;
  coeffs[24] = 32'b11111101100001001011010110000110;
  coeffs[25] = 32'b11111110101111100111010001101110;
  coeffs[26] = 32'b00000000010111111110001101011110;
  coeffs[27] = 32'b00000001110110101110101010000111;
  coeffs[28] = 32'b00000010101010111010000001111100;
  coeffs[29] = 32'b00000010100001010010001000001011;
  coeffs[30] = 32'b00000001011011110110001011011000;
  coeffs[31] = 32'b11111111110010000001100101001000;
  coeffs[32] = 32'b11111110001001101010010111101101;
  coeffs[33] = 32'b11111101001010001001010011000111;
  coeffs[34] = 32'b11111101001110010001111000001100;
  coeffs[35] = 32'b11111110011001011000100000110110;
  coeffs[36] = 32'b00000000010100001011100010001100;
  coeffs[37] = 32'b00000010010010111000011111011011;
  coeffs[38] = 32'b00000011100011011111000110001011;
  coeffs[39] = 32'b00000011011111101001010101110110;
  coeffs[40] = 32'b00000001111100011111001111010010;
  coeffs[41] = 32'b11111111010010010111100110101101;
  coeffs[42] = 32'b11111100011001011001110000001110;
  coeffs[43] = 32'b11111010011010101010011011100011;
  coeffs[44] = 32'b11111010011010001100111111001111;
  coeffs[45] = 32'b11111101000000010110011101000010;
  coeffs[46] = 32'b00000010001001101111111101000100;
  coeffs[47] = 32'b00001001000011100100110011010111;
  coeffs[48] = 32'b00010000010110000000010110001000;
  coeffs[49] = 32'b00010110011010010110100111011111;
  coeffs[50] = 32'b00011001110110101011101000100111;
  coeffs[51] = 32'b00011001110110101011101000100111;
  coeffs[52] = 32'b00010110011010010110100111011111;
  coeffs[53] = 32'b00010000010110000000010110001000;
  coeffs[54] = 32'b00001001000011100100110011010111;
  coeffs[55] = 32'b00000010001001101111111101000100;
  coeffs[56] = 32'b11111101000000010110011101000010;
  coeffs[57] = 32'b11111010011010001100111111001111;
  coeffs[58] = 32'b11111010011010101010011011100011;
  coeffs[59] = 32'b11111100011001011001110000001110;
  coeffs[60] = 32'b11111111010010010111100110101101;
  coeffs[61] = 32'b00000001111100011111001111010010;
  coeffs[62] = 32'b00000011011111101001010101110110;
  coeffs[63] = 32'b00000011100011011111000110001011;
  coeffs[64] = 32'b00000010010010111000011111011011;
  coeffs[65] = 32'b00000000010100001011100010001100;
  coeffs[66] = 32'b11111110011001011000100000110110;
  coeffs[67] = 32'b11111101001110010001111000001100;
  coeffs[68] = 32'b11111101001010001001010011000111;
  coeffs[69] = 32'b11111110001001101010010111101101;
  coeffs[70] = 32'b11111111110010000001100101001000;
  coeffs[71] = 32'b00000001011011110110001011011000;
  coeffs[72] = 32'b00000010100001010010001000001011;
  coeffs[73] = 32'b00000010101010111010000001111100;
  coeffs[74] = 32'b00000001110110101110101010000111;
  coeffs[75] = 32'b00000000010111111110001101011110;
  coeffs[76] = 32'b11111110101111100111010001101110;
  coeffs[77] = 32'b11111101100001001011010110000110;
  coeffs[78] = 32'b11111101000110111111001100000111;
  coeffs[79] = 32'b11111101101010010011111101110010;
  coeffs[80] = 32'b11111111000000110111110001011111;
  coeffs[81] = 32'b00000000110000110111000110011101;
  coeffs[82] = 32'b00000010011000111100101011100000;
  coeffs[83] = 32'b00000011011010011010010100001110;
  coeffs[84] = 32'b00000011100001010010111010001011;
  coeffs[85] = 32'b00000010101001011010110110000000;
  coeffs[86] = 32'b00000000111110000010100110001000;
  coeffs[87] = 32'b11111110110110000001000110111110;
  coeffs[88] = 32'b11111100101100101101111001110001;
  coeffs[89] = 32'b11111010111011010101111011010111;
  coeffs[90] = 32'b11111001110010111111111101010011;
  coeffs[91] = 32'b11111001011010011101011111111110;
  coeffs[92] = 32'b11111001101101111111100111111111;
  coeffs[93] = 32'b11111010100010100111011001000011;
  coeffs[94] = 32'b11111011101001011101101101010111;
  coeffs[95] = 32'b11111100110100010100110110110111;
  coeffs[96] = 32'b11111101110111110111100010111000;
  coeffs[97] = 32'b11111110101101101111000110001010;
  coeffs[98] = 32'b11111111010011101111001000101101;
  coeffs[99] = 32'b11111111101011100010111001111001;
  coeffs[100] = 32'b11111111111000010011001010000001;
  coeffs[101] = 32'b11111111111110000010000011101100;
end


// Combined fine-grain pipelining and parallel processing for 102-tap FIR filter

// Instantiate registers that lie between multiplications in each branch of
// the filter

// Pipelines for computing y(3k)
logic signed [63:0] y_3k_x_3k2_pipeline [NUM_TAPS-1:0];
logic signed [63:0] y_3k_x_3k1_pipeline [NUM_TAPS-1:0];
logic signed [63:0] y_3k_x_3k_pipeline [NUM_TAPS-1:0];

//Pipelines for computing y(3k + 1)
logic signed [63:0] y_3k1_x_3k2_pipeline [NUM_TAPS-1:0];
logic signed [63:0] y_3k1_x_3k1_pipeline [NUM_TAPS-1:0];
logic signed [63:0] y_3k1_x_3k_pipeline [NUM_TAPS-1:0];

//Pipelines for computing y(3k + 2)
logic signed [63:0] y_3k2_x_3k2_pipeline [NUM_TAPS-1:0];
logic signed [63:0] y_3k2_x_3k1_pipeline [NUM_TAPS-1:0];
logic signed [63:0] y_3k2_x_3k_pipeline [NUM_TAPS-1:0];

// Instantiate delay units for input samples
logic signed [31:0] x3k1_delayed;
logic signed [31:0] x3k2_delayed;

always_ff @(posedge clk or posedge rst) begin 
  if (rst) begin 
    x3k1_delayed <= 0;
    x3k2_delayed <= 0;
  end else begin
    x3k1_delayed <= x_in1;
    x3k2_delayed <= x_in2;
  end
end

// Compute y(3k)
always_ff @(posedge clk or posedge rst) begin
  if (rst) begin
    for (int i = NUM_TAPS-1; i >= 0; i=i-1) begin
      y_3k_x_3k_pipeline[i] <= 0;
      y_3k_x_3k1_pipeline[i] <= 0;
      y_3k_x_3k2_pipeline[i] <= 0;
    end
  end else begin
    for (int i = 1; i < NUM_TAPS; i=i+1) begin
      // Shift and multiply by new coefficient
      y_3k_x_3k_pipeline[i] <=  y_3k_x_3k_pipeline[i-1] * coeffs[i-1];
      y_3k_x_3k1_pipeline[i] <= y_3k_x_3k1_pipeline[i-1] * coeffs[i-1];
      y_3k_x_3k2_pipeline[i] <= y_3k_x_3k2_pipeline[i-1] * coeffs[i-1];
    end
    y_3k_x_3k_pipeline[0] <= x_in * coeffs[0];
    y_3k_x_3k1_pipeline[0] <= x3k1_delayed * coeffs[0];
    y_3k_x_3k2_pipeline[0] <= x3k2_delayed * coeffs[0];

  end
end

// Compute y(3k + 1)
always_ff @(posedge clk or posedge rst) begin
  if (rst) begin
    for (int i = NUM_TAPS-1; i >= 0; i=i-1) begin
      y_3k1_x_3k_pipeline[i] <= 0;
      y_3k1_x_3k1_pipeline[i] <= 0;
      y_3k1_x_3k2_pipeline[i] <= 0;
    end
  end else begin
    for (int i = 1; i < NUM_TAPS; i=i+1) begin
      // Shift and multiply by new coefficient
      y_3k1_x_3k_pipeline[i] <= y_3k1_x_3k_pipeline[i-1] * coeffs[i-1];
      y_3k1_x_3k1_pipeline[i] <= y_3k1_x_3k1_pipeline[i-1] * coeffs[i-1];
      y_3k1_x_3k2_pipeline[i] <= y_3k1_x_3k2_pipeline[i-1] * coeffs[i-1];
    end
    y_3k1_x_3k_pipeline[0] <= x_in * coeffs[0];
    y_3k1_x_3k1_pipeline[0] <= x_in1 * coeffs[0];
    y_3k1_x_3k2_pipeline[0] <= x3k2_delayed * coeffs[0];
  end
end

// Compute y(3k + 2)
always_ff @(posedge clk or posedge rst) begin
  if (rst) begin
    for (int i = NUM_TAPS-1; i >= 0; i=i-1) begin
      y_3k2_x_3k_pipeline[i] <= 0;
      y_3k2_x_3k1_pipeline[i] <= 0;
      y_3k2_x_3k2_pipeline[i] <= 0;
    end
  end else begin
    for (int i = 1; i < NUM_TAPS; i=i+1) begin
      // Shift and multiply by new coefficient
      y_3k2_x_3k_pipeline[i] <= y_3k2_x_3k_pipeline[i-1] * coeffs[i-1];
      y_3k2_x_3k1_pipeline[i] <= y_3k2_x_3k1_pipeline[i-1] * coeffs[i-1];
      y_3k2_x_3k2_pipeline[i] <= y_3k2_x_3k2_pipeline[i-1] * coeffs[i-1];
    end
    y_3k2_x_3k_pipeline[0] <= x_in * coeffs[0];
    y_3k2_x_3k1_pipeline[0] <= x_in1 * coeffs[0];
    y_3k2_x_3k2_pipeline[0] <= x_in2 * coeffs[0];
  end
end

// Accumulate the values from the multiplication pipelines
always_comb begin
  for (int i = NUM_TAPS-1; i >= 0; i=i-1) begin
  //y_out = y_3k_x_3k2_pipeline[NUM_TAPS-1] + y_3k_x_3k1_pipeline[NUM_TAPS-1] + y_3k_x_3k_pipeline[NUM_TAPS-1];
  //y_out1 = y_3k1_x_3k2_pipeline[NUM_TAPS-1] + y_3k1_x_3k1_pipeline[NUM_TAPS-1] + y_3k1_x_3k_pipeline[NUM_TAPS-1];
  //y_out2 = y_3k2_x_3k2_pipeline[NUM_TAPS-1] + y_3k2_x_3k1_pipeline[NUM_TAPS-1] + y_3k2_x_3k_pipeline[NUM_TAPS-1];
  y_out = y_3k_x_3k2_pipeline[i] + y_3k_x_3k1_pipeline[i] + y_3k_x_3k_pipeline[i];
  y_out1 = y_3k1_x_3k2_pipeline[i] + y_3k1_x_3k1_pipeline[i] + y_3k1_x_3k_pipeline[i];
  y_out2 = y_3k2_x_3k2_pipeline[i] + y_3k2_x_3k1_pipeline[i] + y_3k2_x_3k_pipeline[i];
  end 
end


endmodule

PipelinedParallelFilter_L=3/filter_tb.sv
`timescale 1ns / 1ps

module filter_tb;

  logic clk;
  logic rst;
  logic signed [31:0] x_in, x_in1, x_in2;
  logic signed [63:0] y_out, y_out1, y_out2;
  logic signed [63:0] y_3k_x_3k_pipeline_out [101:0];

  parameter CLK_PERIOD = 0.5; // 2GHz Clock
  parameter NUM_SAMPLES = 1000;

  filter uut(
    .clk(clk),
    .rst(rst),
    .x_in(x_in),
    .x_in1(x_in1),
    .x_in2(x_in2),
    .y_out(y_out),
    .y_out1(y_out1),
    .y_out2(y_out2)
  );


  // Start the clock
  initial begin
    clk = 0;
    forever #(CLK_PERIOD / 2) clk = ~clk;
  end

  integer file, status;
  integer sample_count;

  logic signed [31:0] sample_data, sample_data1, sample_data2;

  initial begin
    $dumpfile("filter_tb.vcd");
    $dumpvars(0, filter_tb);

    rst = 1;
    x_in = 0;
    sample_count = 0;

    // Open the raw signal data
    file = $fopen("../Python/InputSignals/cosine_wave_100MHz_500MHz.bin", "rb");
    if (file == 0) begin
        $display("Error: Unable to open file!");
        $finish;
    end

    #20 rst = 0;

    // Read and feed samples to the pipeline
    while (sample_count < NUM_SAMPLES) begin
      status = $fread(sample_data, file);
      if (status == 0) begin
        $display("Error: End of file reached or read error!");
        $finish;
      end
      
      status = $fread(sample_data1, file);
      if (status == 0) begin
        $display("Error: End of file reached or read error!");
        $finish;
      end
      
      status = $fread(sample_data2, file);
      if (status == 0) begin
        $display("Error: End of file reached or read error!");
        $finish;
      end

      x_in = sample_data;
      x_in1 = sample_data1;
      x_in2 = sample_data2;
      sample_count = sample_count + 3;
      #CLK_PERIOD;
    end

    $fclose(file);
    #100 $finish;
  end

endmodule

PipelinedParallelFilter_L=3/filter_tb.vcd
$date
	Tue Mar 18 20:53:56 2025
$end
$version
	Icarus Verilog
$end
$timescale
	1ps
$end
$scope module filter_tb $end
$var wire 64 ! y_out2 [63:0] $end
$var wire 64 " y_out1 [63:0] $end
$var wire 64 # y_out [63:0] $end
$var real 1 $ CLK_PERIOD $end
$var parameter 32 % NUM_SAMPLES $end
$var reg 1 & clk $end
$var reg 1 ' rst $end
$var reg 32 ( sample_data [31:0] $end
$var reg 32 ) sample_data1 [31:0] $end
$var reg 32 * sample_data2 [31:0] $end
$var reg 32 + x_in [31:0] $end
$var reg 32 , x_in1 [31:0] $end
$var reg 32 - x_in2 [31:0] $end
$var integer 32 . file [31:0] $end
$var integer 32 / sample_count [31:0] $end
$var integer 32 0 status [31:0] $end
$scope module uut $end
$var wire 1 & clk $end
$var wire 1 ' rst $end
$var wire 32 1 x_in [31:0] $end
$var wire 32 2 x_in1 [31:0] $end
$var wire 32 3 x_in2 [31:0] $end
$var parameter 32 4 NUM_TAPS $end
$var reg 32 5 x3k1_delayed [31:0] $end
$var reg 32 6 x3k2_delayed [31:0] $end
$var reg 64 7 y_out [63:0] $end
$var reg 64 8 y_out1 [63:0] $end
$var reg 64 9 y_out2 [63:0] $end
$scope begin $ivl_for_loop0 $end
$var integer 32 : i [31:0] $end
$upscope $end
$scope begin $ivl_for_loop1 $end
$var integer 32 ; i [31:0] $end
$upscope $end
$scope begin $ivl_for_loop2 $end
$var integer 32 < i [31:0] $end
$upscope $end
$scope begin $ivl_for_loop3 $end
$var integer 32 = i [31:0] $end
$upscope $end
$scope begin $ivl_for_loop4 $end
$var integer 32 > i [31:0] $end
$upscope $end
$scope begin $ivl_for_loop5 $end
$var integer 32 ? i [31:0] $end
$upscope $end
$upscope $end
$upscope $end
$enddefinitions $end
$comment Show the parameter values. $end
$dumpall
b1100110 4
b1111101000 %
r0.5 $
$end
#0
$dumpvars
b0 ?
b11111111111111111111111111111111 >
b0 =
b11111111111111111111111111111111 <
b0 ;
b11111111111111111111111111111111 :
b0 9
b0 8
b0 7
b0 6
b0 5
bx 3
bx 2
b0 1
bx 0
b0 /
b10000000000000000000000000000011 .
bx -
bx ,
b0 +
bx *
bx )
bx (
1'
0&
b0 #
b0 "
b0 !
$end
#250
b11111111111111111111111111111111 >
b11111111111111111111111111111111 <
b11111111111111111111111111111111 :
1&
#500
0&
#750
b11111111111111111111111111111111 >
b11111111111111111111111111111111 <
b11111111111111111111111111111111 :
1&
#1000
0&
#1250
b11111111111111111111111111111111 >
b11111111111111111111111111111111 <
b11111111111111111111111111111111 :
1&
#1500
0&
#1750
b11111111111111111111111111111111 >
b11111111111111111111111111111111 <
b11111111111111111111111111111111 :
1&
#2000
0&
#2250
b11111111111111111111111111111111 >
b11111111111111111111111111111111 <
b11111111111111111111111111111111 :
1&
#2500
0&
#2750
b11111111111111111111111111111111 >
b11111111111111111111111111111111 <
b11111111111111111111111111111111 :
1&
#3000
0&
#3250
b11111111111111111111111111111111 >
b11111111111111111111111111111111 <
b11111111111111111111111111111111 :
1&
#3500
0&
#3750
b11111111111111111111111111111111 >
b11111111111111111111111111111111 <
b11111111111111111111111111111111 :
1&
#4000
0&
#4250
b11111111111111111111111111111111 >
b11111111111111111111111111111111 <
b11111111111111111111111111111111 :
1&
#4500
0&
#4750
b11111111111111111111111111111111 >
b11111111111111111111111111111111 <
b11111111111111111111111111111111 :
1&
#5000
0&
#5250
b11111111111111111111111111111111 >
b11111111111111111111111111111111 <
b11111111111111111111111111111111 :
1&
#5500
0&
#5750
b11111111111111111111111111111111 >
b11111111111111111111111111111111 <
b11111111111111111111111111111111 :
1&
#6000
0&
#6250
b11111111111111111111111111111111 >
b11111111111111111111111111111111 <
b11111111111111111111111111111111 :
1&
#6500
0&
#6750
b11111111111111111111111111111111 >
b11111111111111111111111111111111 <
b11111111111111111111111111111111 :
1&
#7000
0&
#7250
b11111111111111111111111111111111 >
b11111111111111111111111111111111 <
b11111111111111111111111111111111 :
1&
#7500
0&
#7750
b11111111111111111111111111111111 >
b11111111111111111111111111111111 <
b11111111111111111111111111111111 :
1&
#8000
0&
#8250
b11111111111111111111111111111111 >
b11111111111111111111111111111111 <
b11111111111111111111111111111111 :
1&
#8500
0&
#8750
b11111111111111111111111111111111 >
b11111111111111111111111111111111 <
b11111111111111111111111111111111 :
1&
#9000
0&
#9250
b11111111111111111111111111111111 >
b11111111111111111111111111111111 <
b11111111111111111111111111111111 :
1&
#9500
0&
#9750
b11111111111111111111111111111111 >
b11111111111111111111111111111111 <
b11111111111111111111111111111111 :
1&
#10000
0&
#10250
b11111111111111111111111111111111 >
b11111111111111111111111111111111 <
b11111111111111111111111111111111 :
1&
#10500
0&
#10750
b11111111111111111111111111111111 >
b11111111111111111111111111111111 <
b11111111111111111111111111111111 :
1&
#11000
0&
#11250
b11111111111111111111111111111111 >
b11111111111111111111111111111111 <
b11111111111111111111111111111111 :
1&
#11500
0&
#11750
b11111111111111111111111111111111 >
b11111111111111111111111111111111 <
b11111111111111111111111111111111 :
1&
#12000
0&
#12250
b11111111111111111111111111111111 >
b11111111111111111111111111111111 <
b11111111111111111111111111111111 :
1&
#12500
0&
#12750
b11111111111111111111111111111111 >
b11111111111111111111111111111111 <
b11111111111111111111111111111111 :
1&
#13000
0&
#13250
b11111111111111111111111111111111 >
b11111111111111111111111111111111 <
b11111111111111111111111111111111 :
1&
#13500
0&
#13750
b11111111111111111111111111111111 >
b11111111111111111111111111111111 <
b11111111111111111111111111111111 :
1&
#14000
0&
#14250
b11111111111111111111111111111111 >
b11111111111111111111111111111111 <
b11111111111111111111111111111111 :
1&
#14500
0&
#14750
b11111111111111111111111111111111 >
b11111111111111111111111111111111 <
b11111111111111111111111111111111 :
1&
#15000
0&
#15250
b11111111111111111111111111111111 >
b11111111111111111111111111111111 <
b11111111111111111111111111111111 :
1&
#15500
0&
#15750
b11111111111111111111111111111111 >
b11111111111111111111111111111111 <
b11111111111111111111111111111111 :
1&
#16000
0&
#16250
b11111111111111111111111111111111 >
b11111111111111111111111111111111 <
b11111111111111111111111111111111 :
1&
#16500
0&
#16750
b11111111111111111111111111111111 >
b11111111111111111111111111111111 <
b11111111111111111111111111111111 :
1&
#17000
0&
#17250
b11111111111111111111111111111111 >
b11111111111111111111111111111111 <
b11111111111111111111111111111111 :
1&
#17500
0&
#17750
b11111111111111111111111111111111 >
b11111111111111111111111111111111 <
b11111111111111111111111111111111 :
1&
#18000
0&
#18250
b11111111111111111111111111111111 >
b11111111111111111111111111111111 <
b11111111111111111111111111111111 :
1&
#18500
0&
#18750
b11111111111111111111111111111111 >
b11111111111111111111111111111111 <
b11111111111111111111111111111111 :
1&
#19000
0&
#19250
b11111111111111111111111111111111 >
b11111111111111111111111111111111 <
b11111111111111111111111111111111 :
1&
#19500
0&
#19750
b11111111111111111111111111111111 >
b11111111111111111111111111111111 <
b11111111111111111111111111111111 :
1&
#20000
0&
b11 /
b1100111100011011101111001101101 -
b1100111100011011101111001101101 3
b1111001101111000011100001001100 ,
b1111001101111000011100001001100 2
b1111111111111111111111111111111 +
b1111111111111111111111111111111 1
b1100111100011011101111001101101 *
b1111001101111000011100001001100 )
b100 0
b1111111111111111111111111111111 (
0'
#20250
b1100111100011011101111001101101 6
b1111001101111000011100001001100 5
b1100101 ?
b1100101 =
b1100101 ;
1&
#20500
0&
b110 /
b0 -
b0 3
b100111100011011101111001101110 ,
b100111100011011101111001101110 2
b1001011001111001000110000010001 +
b1001011001111001000110000010001 1
b0 *
b100111100011011101111001101110 )
b1001011001111001000110000010001 (
#20750
b0 6
b100111100011011101111001101110 5
b1100101 ?
b1100101 =
b1100101 ;
1&
#21000
0&
b1001 /
b10011000011100100010000110010011 -
b10011000011100100010000110010011 3
b10110100110000110111001111101111 ,
b10110100110000110111001111101111 2
b11011000011100100010000110010010 +
b11011000011100100010000110010010 1
b10011000011100100010000110010011 *
b10110100110000110111001111101111 )
b11011000011100100010000110010010 (
#21250
b10011000011100100010000110010011 6
b10110100110000110111001111101111 5
b1100101 ?
b1100101 =
b1100101 ;
1&
#21500
0&
b1100 /
b10000110010000111100011110110100 -
b10000110010000111100011110110100 3
b10000000000000000000000000000001 ,
b10000000000000000000000000000001 2
b10000110010000111100011110110100 +
b10000110010000111100011110110100 1
b10000110010000111100011110110100 *
b10000000000000000000000000000001 )
b10000110010000111100011110110100 (
#21750
b10000110010000111100011110110100 6
b10000000000000000000000000000001 5
b1100101 ?
b1100101 =
b1100101 ;
1&
#22000
0&
b1111 /
b11011000011100100010000110010010 -
b11011000011100100010000110010010 3
b10110100110000110111001111101111 ,
b10110100110000110111001111101111 2
b10011000011100100010000110010011 +
b10011000011100100010000110010011 1
b11011000011100100010000110010010 *
b10110100110000110111001111101111 )
b10011000011100100010000110010011 (
#22250
b11011000011100100010000110010010 6
b10110100110000110111001111101111 5
b1100101 ?
b1100101 =
b1100101 ;
1&
#22500
0&
b10010 /
b1001011001111001000110000010001 -
b1001011001111001000110000010001 3
b100111100011011101111001101110 ,
b100111100011011101111001101110 2
b0 +
b0 1
b1001011001111001000110000010001 *
b100111100011011101111001101110 )
b0 (
#22750
b1001011001111001000110000010001 6
b100111100011011101111001101110 5
b1100101 ?
b1100101 =
b1100101 ;
1&
#23000
0&
b10101 /
b1111111111111111111111111111111 -
b1111111111111111111111111111111 3
b1111001101111000011100001001100 ,
b1111001101111000011100001001100 2
b1100111100011011101111001101101 +
b1100111100011011101111001101101 1
b1111111111111111111111111111111 *
b1111001101111000011100001001100 )
b1100111100011011101111001101101 (
#23250
b1111111111111111111111111111111 6
b1111001101111000011100001001100 5
b1100101 ?
b1100101 =
b1100101 ;
1&
#23500
0&
b11000 /
b1001011001111001000110000010001 -
b1001011001111001000110000010001 3
b1100111100011011101111001101101 ,
b1100111100011011101111001101101 2
b1111001101111000011100001001100 +
b1111001101111000011100001001100 1
b1001011001111001000110000010001 *
b1100111100011011101111001101101 )
b1111001101111000011100001001100 (
#23750
b1001011001111001000110000010001 6
b1100111100011011101111001101101 5
b1100101 ?
b1100101 =
b1100101 ;
1&
#24000
0&
b11011 /
b11011000011100100010000110010010 -
b11011000011100100010000110010010 3
b0 ,
b0 2
b100111100011011101111001101110 +
b100111100011011101111001101110 1
b11011000011100100010000110010010 *
b0 )
b100111100011011101111001101110 (
#24250
b11011000011100100010000110010010 6
b0 5
b1100101 ?
b1100101 =
b1100101 ;
1&
#24500
0&
b11110 /
b10000110010000111100011110110100 -
b10000110010000111100011110110100 3
b10011000011100100010000110010011 ,
b10011000011100100010000110010011 2
b10110100110000110111001111101111 +
b10110100110000110111001111101111 1
b10000110010000111100011110110100 *
b10011000011100100010000110010011 )
b10110100110000110111001111101111 (
#24750
b10000110010000111100011110110100 6
b10011000011100100010000110010011 5
b1100101 ?
b1100101 =
b1100101 ;
1&
#25000
0&
b100001 /
b10011000011100100010000110010011 -
b10011000011100100010000110010011 3
b10000110010000111100011110110100 ,
b10000110010000111100011110110100 2
b10000000000000000000000000000001 +
b10000000000000000000000000000001 1
b10011000011100100010000110010011 *
b10000110010000111100011110110100 )
b10000000000000000000000000000001 (
#25250
b10011000011100100010000110010011 6
b10000110010000111100011110110100 5
b1100101 ?
b1100101 =
b1100101 ;
1&
#25500
0&
b100100 /
b0 -
b0 3
b11011000011100100010000110010010 ,
b11011000011100100010000110010010 2
b10110100110000110111001111101111 +
b10110100110000110111001111101111 1
b0 *
b11011000011100100010000110010010 )
b10110100110000110111001111101111 (
#25750
b0 6
b11011000011100100010000110010010 5
b1100101 ?
b1100101 =
b1100101 ;
1&
#26000
0&
b100111 /
b1100111100011011101111001101101 -
b1100111100011011101111001101101 3
b1001011001111001000110000010001 ,
b1001011001111001000110000010001 2
b100111100011011101111001101110 +
b100111100011011101111001101110 1
b1100111100011011101111001101101 *
b1001011001111001000110000010001 )
b100111100011011101111001101110 (
#26250
b1100111100011011101111001101101 6
b1001011001111001000110000010001 5
b1100101 ?
b1100101 =
b1100101 ;
1&
#26500
0&
b101010 /
b1111001101111000011100001001100 -
b1111001101111000011100001001100 3
b1111111111111111111111111111111 ,
b1111111111111111111111111111111 2
b1111001101111000011100001001100 +
b1111001101111000011100001001100 1
b1111001101111000011100001001100 *
b1111111111111111111111111111111 )
b1111001101111000011100001001100 (
#26750
b1111001101111000011100001001100 6
b1111111111111111111111111111111 5
b1100101 ?
b1100101 =
b1100101 ;
1&
#27000
0&
b101101 /
b100111100011011101111001101110 -
b100111100011011101111001101110 3
b1001011001111001000110000010001 ,
b1001011001111001000110000010001 2
b1100111100011011101111001101101 +
b1100111100011011101111001101101 1
b100111100011011101111001101110 *
b1001011001111001000110000010001 )
b1100111100011011101111001101101 (
#27250
b100111100011011101111001101110 6
b1001011001111001000110000010001 5
b1100101 ?
b1100101 =
b1100101 ;
1&
#27500
0&
b110000 /
b10110100110000110111001111101111 -
b10110100110000110111001111101111 3
b11011000011100100010000110010010 ,
b11011000011100100010000110010010 2
b0 +
b0 1
b10110100110000110111001111101111 *
b11011000011100100010000110010010 )
b0 (
#27750
b10110100110000110111001111101111 6
b11011000011100100010000110010010 5
b1100101 ?
b1100101 =
b1100101 ;
1&
#28000
0&
b110011 /
b10000000000000000000000000000001 -
b10000000000000000000000000000001 3
b10000110010000111100011110110100 ,
b10000110010000111100011110110100 2
b10011000011100100010000110010011 +
b10011000011100100010000110010011 1
b10000000000000000000000000000001 *
b10000110010000111100011110110100 )
b10011000011100100010000110010011 (
#28250
b10000000000000000000000000000001 6
b10000110010000111100011110110100 5
b1100101 ?
b1100101 =
b1100101 ;
1&
#28500
0&
b110110 /
b10110100110000110111001111101111 -
b10110100110000110111001111101111 3
b10011000011100100010000110010011 ,
b10011000011100100010000110010011 2
b10000110010000111100011110110100 +
b10000110010000111100011110110100 1
b10110100110000110111001111101111 *
b10011000011100100010000110010011 )
b10000110010000111100011110110100 (
#28750
b10110100110000110111001111101111 6
b10011000011100100010000110010011 5
b1100101 ?
b1100101 =
b1100101 ;
1&
#29000
0&
b111001 /
b100111100011011101111001101110 -
b100111100011011101111001101110 3
b0 ,
b0 2
b11011000011100100010000110010010 +
b11011000011100100010000110010010 1
b100111100011011101111001101110 *
b0 )
b11011000011100100010000110010010 (
#29250
b100111100011011101111001101110 6
b0 5
b1100101 ?
b1100101 =
b1100101 ;
1&
#29500
0&
b111100 /
b1111001101111000011100001001100 -
b1111001101111000011100001001100 3
b1100111100011011101111001101101 ,
b1100111100011011101111001101101 2
b1001011001111001000110000010001 +
b1001011001111001000110000010001 1
b1111001101111000011100001001100 *
b1100111100011011101111001101101 )
b1001011001111001000110000010001 (
#29750
b1111001101111000011100001001100 6
b1100111100011011101111001101101 5
b1100101 ?
b1100101 =
b1100101 ;
1&
#30000
0&
b111111 /
b1100111100011011101111001101101 -
b1100111100011011101111001101101 3
b1111001101111000011100001001100 ,
b1111001101111000011100001001100 2
b1111111111111111111111111111111 +
b1111111111111111111111111111111 1
b1100111100011011101111001101101 *
b1111001101111000011100001001100 )
b1111111111111111111111111111111 (
#30250
b1100111100011011101111001101101 6
b1111001101111000011100001001100 5
b1100101 ?
b1100101 =
b1100101 ;
1&
#30500
0&
b1000010 /
b0 -
b0 3
b100111100011011101111001101110 ,
b100111100011011101111001101110 2
b1001011001111001000110000010001 +
b1001011001111001000110000010001 1
b0 *
b100111100011011101111001101110 )
b1001011001111001000110000010001 (
#30750
b0 6
b100111100011011101111001101110 5
b1100101 ?
b1100101 =
b1100101 ;
1&
#31000
0&
b1000101 /
b10011000011100100010000110010011 -
b10011000011100100010000110010011 3
b10110100110000110111001111101111 ,
b10110100110000110111001111101111 2
b11011000011100100010000110010010 +
b11011000011100100010000110010010 1
b10011000011100100010000110010011 *
b10110100110000110111001111101111 )
b11011000011100100010000110010010 (
#31250
b10011000011100100010000110010011 6
b10110100110000110111001111101111 5
b1100101 ?
b1100101 =
b1100101 ;
1&
#31500
0&
b1001000 /
b10000110010000111100011110110100 -
b10000110010000111100011110110100 3
b10000000000000000000000000000001 ,
b10000000000000000000000000000001 2
b10000110010000111100011110110100 +
b10000110010000111100011110110100 1
b10000110010000111100011110110100 *
b10000000000000000000000000000001 )
b10000110010000111100011110110100 (
#31750
b10000110010000111100011110110100 6
b10000000000000000000000000000001 5
b1100101 ?
b1100101 =
b1100101 ;
1&
#32000
0&
b1001011 /
b11011000011100100010000110010010 -
b11011000011100100010000110010010 3
b10110100110000110111001111101111 ,
b10110100110000110111001111101111 2
b10011000011100100010000110010011 +
b10011000011100100010000110010011 1
b11011000011100100010000110010010 *
b10110100110000110111001111101111 )
b10011000011100100010000110010011 (
#32250
b11011000011100100010000110010010 6
b10110100110000110111001111101111 5
b1100101 ?
b1100101 =
b1100101 ;
1&
#32500
0&
b1001110 /
b1001011001111001000110000010001 -
b1001011001111001000110000010001 3
b100111100011011101111001101110 ,
b100111100011011101111001101110 2
b0 +
b0 1
b1001011001111001000110000010001 *
b100111100011011101111001101110 )
b0 (
#32750
b1001011001111001000110000010001 6
b100111100011011101111001101110 5
b1100101 ?
b1100101 =
b1100101 ;
1&
