PipelinedFilter/filter.sv
`timescale 1ns / 1ps

module filter(
  input logic clk,
  input logic rst,
  input logic signed [31:0] x_in,
  output logic signed [63:0] y_out
);

parameter NUM_TAPS = 102;

logic signed [31:0] coeffs [0:102];

initial begin 
  coeffs[0] = 32'b11111111111110000010000011101100;
  coeffs[1] = 32'b11111111111000010011001010000001;
  coeffs[2] = 32'b11111111101011100010111001111001;
  coeffs[3] = 32'b11111111010011101111001000101101;
  coeffs[4] = 32'b11111110101101101111000110001010;
  coeffs[5] = 32'b11111101110111110111100010111000;
  coeffs[6] = 32'b11111100110100010100110110110111;
  coeffs[7] = 32'b11111011101001011101101101010111;
  coeffs[8] = 32'b11111010100010100111011001000011;
  coeffs[9] = 32'b11111001101101111111100111111111;
  coeffs[10] = 32'b11111001011010011101011111111110;
  coeffs[11] = 32'b11111001110010111111111101010011;
  coeffs[12] = 32'b11111010111011010101111011010111;
  coeffs[13] = 32'b11111100101100101101111001110001;
  coeffs[14] = 32'b11111110110110000001000110111110;
  coeffs[15] = 32'b00000000111110000010100110001000;
  coeffs[16] = 32'b00000010101001011010110110000000;
  coeffs[17] = 32'b00000011100001010010111010001011;
  coeffs[18] = 32'b00000011011010011010010100001110;
  coeffs[19] = 32'b00000010011000111100101011100000;
  coeffs[20] = 32'b00000000110000110111000110011101;
  coeffs[21] = 32'b11111111000000110111110001011111;
  coeffs[22] = 32'b11111101101010010011111101110010;
  coeffs[23] = 32'b11111101000110111111001100000111;
  coeffs[24] = 32'b11111101100001001011010110000110;
  coeffs[25] = 32'b11111110101111100111010001101110;
  coeffs[26] = 32'b00000000010111111110001101011110;
  coeffs[27] = 32'b00000001110110101110101010000111;
  coeffs[28] = 32'b00000010101010111010000001111100;
  coeffs[29] = 32'b00000010100001010010001000001011;
  coeffs[30] = 32'b00000001011011110110001011011000;
  coeffs[31] = 32'b11111111110010000001100101001000;
  coeffs[32] = 32'b11111110001001101010010111101101;
  coeffs[33] = 32'b11111101001010001001010011000111;
  coeffs[34] = 32'b11111101001110010001111000001100;
  coeffs[35] = 32'b11111110011001011000100000110110;
  coeffs[36] = 32'b00000000010100001011100010001100;
  coeffs[37] = 32'b00000010010010111000011111011011;
  coeffs[38] = 32'b00000011100011011111000110001011;
  coeffs[39] = 32'b00000011011111101001010101110110;
  coeffs[40] = 32'b00000001111100011111001111010010;
  coeffs[41] = 32'b11111111010010010111100110101101;
  coeffs[42] = 32'b11111100011001011001110000001110;
  coeffs[43] = 32'b11111010011010101010011011100011;
  coeffs[44] = 32'b11111010011010001100111111001111;
  coeffs[45] = 32'b11111101000000010110011101000010;
  coeffs[46] = 32'b00000010001001101111111101000100;
  coeffs[47] = 32'b00001001000011100100110011010111;
  coeffs[48] = 32'b00010000010110000000010110001000;
  coeffs[49] = 32'b00010110011010010110100111011111;
  coeffs[50] = 32'b00011001110110101011101000100111;
  coeffs[51] = 32'b00011001110110101011101000100111;
  coeffs[52] = 32'b00010110011010010110100111011111;
  coeffs[53] = 32'b00010000010110000000010110001000;
  coeffs[54] = 32'b00001001000011100100110011010111;
  coeffs[55] = 32'b00000010001001101111111101000100;
  coeffs[56] = 32'b11111101000000010110011101000010;
  coeffs[57] = 32'b11111010011010001100111111001111;
  coeffs[58] = 32'b11111010011010101010011011100011;
  coeffs[59] = 32'b11111100011001011001110000001110;
  coeffs[60] = 32'b11111111010010010111100110101101;
  coeffs[61] = 32'b00000001111100011111001111010010;
  coeffs[62] = 32'b00000011011111101001010101110110;
  coeffs[63] = 32'b00000011100011011111000110001011;
  coeffs[64] = 32'b00000010010010111000011111011011;
  coeffs[65] = 32'b00000000010100001011100010001100;
  coeffs[66] = 32'b11111110011001011000100000110110;
  coeffs[67] = 32'b11111101001110010001111000001100;
  coeffs[68] = 32'b11111101001010001001010011000111;
  coeffs[69] = 32'b11111110001001101010010111101101;
  coeffs[70] = 32'b11111111110010000001100101001000;
  coeffs[71] = 32'b00000001011011110110001011011000;
  coeffs[72] = 32'b00000010100001010010001000001011;
  coeffs[73] = 32'b00000010101010111010000001111100;
  coeffs[74] = 32'b00000001110110101110101010000111;
  coeffs[75] = 32'b00000000010111111110001101011110;
  coeffs[76] = 32'b11111110101111100111010001101110;
  coeffs[77] = 32'b11111101100001001011010110000110;
  coeffs[78] = 32'b11111101000110111111001100000111;
  coeffs[79] = 32'b11111101101010010011111101110010;
  coeffs[80] = 32'b11111111000000110111110001011111;
  coeffs[81] = 32'b00000000110000110111000110011101;
  coeffs[82] = 32'b00000010011000111100101011100000;
  coeffs[83] = 32'b00000011011010011010010100001110;
  coeffs[84] = 32'b00000011100001010010111010001011;
  coeffs[85] = 32'b00000010101001011010110110000000;
  coeffs[86] = 32'b00000000111110000010100110001000;
  coeffs[87] = 32'b11111110110110000001000110111110;
  coeffs[88] = 32'b11111100101100101101111001110001;
  coeffs[89] = 32'b11111010111011010101111011010111;
  coeffs[90] = 32'b11111001110010111111111101010011;
  coeffs[91] = 32'b11111001011010011101011111111110;
  coeffs[92] = 32'b11111001101101111111100111111111;
  coeffs[93] = 32'b11111010100010100111011001000011;
  coeffs[94] = 32'b11111011101001011101101101010111;
  coeffs[95] = 32'b11111100110100010100110110110111;
  coeffs[96] = 32'b11111101110111110111100010111000;
  coeffs[97] = 32'b11111110101101101111000110001010;
  coeffs[98] = 32'b11111111010011101111001000101101;
  coeffs[99] = 32'b11111111101011100010111001111001;
  coeffs[100] = 32'b11111111111000010011001010000001;
  coeffs[101] = 32'b11111111111110000010000011101100;
end

// Pipeline register array for partial sums – one register per stage.
logic signed [63:0] stage [0:NUM_TAPS];

// Stage NUM_TAPS: Multiply the current input by the last coefficient.
always_ff @(posedge clk or posedge rst) begin
    if (rst)
        stage[NUM_TAPS] <= 64'sh0;
    else
        stage[NUM_TAPS] <= x_in * coeffs[NUM_TAPS-1];
end

// Generate the pipeline stages.
genvar i;
generate
for (i = NUM_TAPS-1; i > 0; i = i - 1) begin
    always_ff @(posedge clk or posedge rst) begin
        if (rst)
            stage[i] <= 64'sh0;
        else
            stage[i] <= (x_in * coeffs[i-1]) + stage[i+1];
    end
end
endgenerate

always_ff @(posedge clk) begin
  if (rst) begin
    stage[0] <= 64'sh0;  
  end 
  else
    stage[0] <= (x_in * coeffs[0]);
end

// Final output: scale back to Q31 by shifting right 31 bits.
always_ff @(posedge clk or posedge rst) begin
    if (rst)
        y_out <= 32'sh0;
    else
        y_out <= stage[1] >>> 31;
end

endmodule

PipelinedFilter/filter_tb.sv
`timescale 1ns / 1ps

module filter_tb;

  logic clk;
  logic rst;
  logic signed [31:0] x_in;
  logic signed [63:0] y_out;

  parameter CLK_PERIOD = 0.5; // 2GHz Clock
  parameter NUM_SAMPLES = 1000;

  filter uut(
    .clk(clk),
    .rst(rst),
    .x_in(x_in),
    .y_out(y_out)
  );


  // Start the clock
  initial begin
    clk = 0;
    forever #(CLK_PERIOD / 2) clk = ~clk;
  end

  integer file, status;
  integer sample_count;

  logic signed [31:0] sample_data;

  initial begin
    $dumpfile("filter_tb.vcd");
    $dumpvars(0, filter_tb);

    rst = 1;
    x_in = 0;
    sample_count = 0;

    // Open the raw signal data
    file = $fopen("../Python/InputSignals/cosine_wave_100MHz_500MHz.bin", "rb");
    if (file == 0) begin
        $display("Error: Unable to open file!");
        $finish;
    end

    #20 rst = 0;

    // Read and feed samples to the pipeline
    while (sample_count < NUM_SAMPLES) begin
      status = $fread(sample_data, file);
      if (status == 0) begin
        $display("Error: End of file reached or read error!");
        $finish;
      end

      x_in = sample_data;
      sample_count = sample_count + 1;
      #CLK_PERIOD;
    end

    $fclose(file);
    #100 $finish;
  end

endmodule

PipelinedFilter/filter_tb.vcd
$date
	Tue Mar 18 14:22:21 2025
$end
$version
	Icarus Verilog
$end
$timescale
	1ps
$end
$scope module filter_tb $end
$var wire 64 ! y_out [63:0] $end
$var real 1 " CLK_PERIOD $end
$var parameter 32 # NUM_SAMPLES $end
$var reg 1 $ clk $end
$var reg 1 % rst $end
$var reg 32 & sample_data [31:0] $end
$var reg 32 ' x_in [31:0] $end
$var integer 32 ( file [31:0] $end
$var integer 32 ) sample_count [31:0] $end
$var integer 32 * status [31:0] $end
$scope module uut $end
$var wire 1 $ clk $end
$var wire 1 % rst $end
$var wire 32 + x_in [31:0] $end
$var parameter 32 , NUM_TAPS $end
$var reg 64 - y_out [63:0] $end
$scope begin pipe_stages[1] $end
$var parameter 2 . i $end
$upscope $end
$scope begin pipe_stages[2] $end
$var parameter 3 / i $end
$upscope $end
$scope begin pipe_stages[3] $end
$var parameter 3 0 i $end
$upscope $end
$scope begin pipe_stages[4] $end
$var parameter 4 1 i $end
$upscope $end
$scope begin pipe_stages[5] $end
$var parameter 4 2 i $end
$upscope $end
$scope begin pipe_stages[6] $end
$var parameter 4 3 i $end
$upscope $end
$scope begin pipe_stages[7] $end
$var parameter 4 4 i $end
$upscope $end
$scope begin pipe_stages[8] $end
$var parameter 5 5 i $end
$upscope $end
$scope begin pipe_stages[9] $end
$var parameter 5 6 i $end
$upscope $end
$scope begin pipe_stages[10] $end
$var parameter 5 7 i $end
$upscope $end
$scope begin pipe_stages[11] $end
$var parameter 5 8 i $end
$upscope $end
$scope begin pipe_stages[12] $end
$var parameter 5 9 i $end
$upscope $end
$scope begin pipe_stages[13] $end
$var parameter 5 : i $end
$upscope $end
$scope begin pipe_stages[14] $end
$var parameter 5 ; i $end
$upscope $end
$scope begin pipe_stages[15] $end
$var parameter 5 < i $end
$upscope $end
$scope begin pipe_stages[16] $end
$var parameter 6 = i $end
$upscope $end
$scope begin pipe_stages[17] $end
$var parameter 6 > i $end
$upscope $end
$scope begin pipe_stages[18] $end
$var parameter 6 ? i $end
$upscope $end
$scope begin pipe_stages[19] $end
$var parameter 6 @ i $end
$upscope $end
$scope begin pipe_stages[20] $end
$var parameter 6 A i $end
$upscope $end
$scope begin pipe_stages[21] $end
$var parameter 6 B i $end
$upscope $end
$scope begin pipe_stages[22] $end
$var parameter 6 C i $end
$upscope $end
$scope begin pipe_stages[23] $end
$var parameter 6 D i $end
$upscope $end
$scope begin pipe_stages[24] $end
$var parameter 6 E i $end
$upscope $end
$scope begin pipe_stages[25] $end
$var parameter 6 F i $end
$upscope $end
$scope begin pipe_stages[26] $end
$var parameter 6 G i $end
$upscope $end
$scope begin pipe_stages[27] $end
$var parameter 6 H i $end
$upscope $end
$scope begin pipe_stages[28] $end
$var parameter 6 I i $end
$upscope $end
$scope begin pipe_stages[29] $end
$var parameter 6 J i $end
$upscope $end
$scope begin pipe_stages[30] $end
$var parameter 6 K i $end
$upscope $end
$scope begin pipe_stages[31] $end
$var parameter 6 L i $end
$upscope $end
$scope begin pipe_stages[32] $end
$var parameter 7 M i $end
$upscope $end
$scope begin pipe_stages[33] $end
$var parameter 7 N i $end
$upscope $end
$scope begin pipe_stages[34] $end
$var parameter 7 O i $end
$upscope $end
$scope begin pipe_stages[35] $end
$var parameter 7 P i $end
$upscope $end
$scope begin pipe_stages[36] $end
$var parameter 7 Q i $end
$upscope $end
$scope begin pipe_stages[37] $end
$var parameter 7 R i $end
$upscope $end
$scope begin pipe_stages[38] $end
$var parameter 7 S i $end
$upscope $end
$scope begin pipe_stages[39] $end
$var parameter 7 T i $end
$upscope $end
$scope begin pipe_stages[40] $end
$var parameter 7 U i $end
$upscope $end
$scope begin pipe_stages[41] $end
$var parameter 7 V i $end
$upscope $end
$scope begin pipe_stages[42] $end
$var parameter 7 W i $end
$upscope $end
$scope begin pipe_stages[43] $end
$var parameter 7 X i $end
$upscope $end
$scope begin pipe_stages[44] $end
$var parameter 7 Y i $end
$upscope $end
$scope begin pipe_stages[45] $end
$var parameter 7 Z i $end
$upscope $end
$scope begin pipe_stages[46] $end
$var parameter 7 [ i $end
$upscope $end
$scope begin pipe_stages[47] $end
$var parameter 7 \ i $end
$upscope $end
$scope begin pipe_stages[48] $end
$var parameter 7 ] i $end
$upscope $end
$scope begin pipe_stages[49] $end
$var parameter 7 ^ i $end
$upscope $end
$scope begin pipe_stages[50] $end
$var parameter 7 _ i $end
$upscope $end
$scope begin pipe_stages[51] $end
$var parameter 7 ` i $end
$upscope $end
$scope begin pipe_stages[52] $end
$var parameter 7 a i $end
$upscope $end
$scope begin pipe_stages[53] $end
$var parameter 7 b i $end
$upscope $end
$scope begin pipe_stages[54] $end
$var parameter 7 c i $end
$upscope $end
$scope begin pipe_stages[55] $end
$var parameter 7 d i $end
$upscope $end
$scope begin pipe_stages[56] $end
$var parameter 7 e i $end
$upscope $end
$scope begin pipe_stages[57] $end
$var parameter 7 f i $end
$upscope $end
$scope begin pipe_stages[58] $end
$var parameter 7 g i $end
$upscope $end
$scope begin pipe_stages[59] $end
$var parameter 7 h i $end
$upscope $end
$scope begin pipe_stages[60] $end
$var parameter 7 i i $end
$upscope $end
$scope begin pipe_stages[61] $end
$var parameter 7 j i $end
$upscope $end
$scope begin pipe_stages[62] $end
$var parameter 7 k i $end
$upscope $end
$scope begin pipe_stages[63] $end
$var parameter 7 l i $end
$upscope $end
$scope begin pipe_stages[64] $end
$var parameter 8 m i $end
$upscope $end
$scope begin pipe_stages[65] $end
$var parameter 8 n i $end
$upscope $end
$scope begin pipe_stages[66] $end
$var parameter 8 o i $end
$upscope $end
$scope begin pipe_stages[67] $end
$var parameter 8 p i $end
$upscope $end
$scope begin pipe_stages[68] $end
$var parameter 8 q i $end
$upscope $end
$scope begin pipe_stages[69] $end
$var parameter 8 r i $end
$upscope $end
$scope begin pipe_stages[70] $end
$var parameter 8 s i $end
$upscope $end
$scope begin pipe_stages[71] $end
$var parameter 8 t i $end
$upscope $end
$scope begin pipe_stages[72] $end
$var parameter 8 u i $end
$upscope $end
$scope begin pipe_stages[73] $end
$var parameter 8 v i $end
$upscope $end
$scope begin pipe_stages[74] $end
$var parameter 8 w i $end
$upscope $end
$scope begin pipe_stages[75] $end
$var parameter 8 x i $end
$upscope $end
$scope begin pipe_stages[76] $end
$var parameter 8 y i $end
$upscope $end
$scope begin pipe_stages[77] $end
$var parameter 8 z i $end
$upscope $end
$scope begin pipe_stages[78] $end
$var parameter 8 { i $end
$upscope $end
$scope begin pipe_stages[79] $end
$var parameter 8 | i $end
$upscope $end
$scope begin pipe_stages[80] $end
$var parameter 8 } i $end
$upscope $end
$scope begin pipe_stages[81] $end
$var parameter 8 ~ i $end
$upscope $end
$scope begin pipe_stages[82] $end
$var parameter 8 !" i $end
$upscope $end
$scope begin pipe_stages[83] $end
$var parameter 8 "" i $end
$upscope $end
$scope begin pipe_stages[84] $end
$var parameter 8 #" i $end
$upscope $end
$scope begin pipe_stages[85] $end
$var parameter 8 $" i $end
$upscope $end
$scope begin pipe_stages[86] $end
$var parameter 8 %" i $end
$upscope $end
$scope begin pipe_stages[87] $end
$var parameter 8 &" i $end
$upscope $end
$scope begin pipe_stages[88] $end
$var parameter 8 '" i $end
$upscope $end
$scope begin pipe_stages[89] $end
$var parameter 8 (" i $end
$upscope $end
$scope begin pipe_stages[90] $end
$var parameter 8 )" i $end
$upscope $end
$scope begin pipe_stages[91] $end
$var parameter 8 *" i $end
$upscope $end
$scope begin pipe_stages[92] $end
$var parameter 8 +" i $end
$upscope $end
$scope begin pipe_stages[93] $end
$var parameter 8 ," i $end
$upscope $end
$scope begin pipe_stages[94] $end
$var parameter 8 -" i $end
$upscope $end
$scope begin pipe_stages[95] $end
$var parameter 8 ." i $end
$upscope $end
$scope begin pipe_stages[96] $end
$var parameter 8 /" i $end
$upscope $end
$scope begin pipe_stages[97] $end
$var parameter 8 0" i $end
$upscope $end
$scope begin pipe_stages[98] $end
$var parameter 8 1" i $end
$upscope $end
$scope begin pipe_stages[99] $end
$var parameter 8 2" i $end
$upscope $end
$scope begin pipe_stages[100] $end
$var parameter 8 3" i $end
$upscope $end
$scope begin pipe_stages[101] $end
$var parameter 8 4" i $end
$upscope $end
$upscope $end
$upscope $end
$enddefinitions $end
$comment Show the parameter values. $end
$dumpall
b1100101 4"
b1100100 3"
b1100011 2"
b1100010 1"
b1100001 0"
b1100000 /"
b1011111 ."
b1011110 -"
b1011101 ,"
b1011100 +"
b1011011 *"
b1011010 )"
b1011001 ("
b1011000 '"
b1010111 &"
b1010110 %"
b1010101 $"
b1010100 #"
b1010011 ""
b1010010 !"
b1010001 ~
b1010000 }
b1001111 |
b1001110 {
b1001101 z
b1001100 y
b1001011 x
b1001010 w
b1001001 v
b1001000 u
b1000111 t
b1000110 s
b1000101 r
b1000100 q
b1000011 p
b1000010 o
b1000001 n
b1000000 m
b111111 l
b111110 k
b111101 j
b111100 i
b111011 h
b111010 g
b111001 f
b111000 e
b110111 d
b110110 c
b110101 b
b110100 a
b110011 `
b110010 _
b110001 ^
b110000 ]
b101111 \
b101110 [
b101101 Z
b101100 Y
b101011 X
b101010 W
b101001 V
b101000 U
b100111 T
b100110 S
b100101 R
b100100 Q
b100011 P
b100010 O
b100001 N
b100000 M
b11111 L
b11110 K
b11101 J
b11100 I
b11011 H
b11010 G
b11001 F
b11000 E
b10111 D
b10110 C
b10101 B
b10100 A
b10011 @
b10010 ?
b10001 >
b10000 =
b1111 <
b1110 ;
b1101 :
b1100 9
b1011 8
b1010 7
b1001 6
b1000 5
b111 4
b110 3
b101 2
b100 1
b11 0
b10 /
b1 .
b1100110 ,
b1111101000 #
r0.5 "
$end
#0
$dumpvars
b0 -
b0 +
bx *
b0 )
b10000000000000000000000000000011 (
b0 '
bx &
1%
0$
b0 !
$end
#250
1$
#500
0$
#750
1$
#1000
0$
#1250
1$
#1500
0$
#1750
1$
#2000
0$
#2250
1$
#2500
0$
#2750
1$
#3000
0$
#3250
1$
#3500
0$
#3750
1$
#4000
0$
#4250
1$
#4500
0$
#4750
1$
#5000
0$
#5250
1$
#5500
0$
#5750
1$
#6000
0$
#6250
1$
#6500
0$
#6750
1$
#7000
0$
#7250
1$
#7500
0$
#7750
1$
#8000
0$
#8250
1$
#8500
0$
#8750
1$
#9000
0$
#9250
1$
#9500
0$
#9750
1$
#10000
0$
#10250
1$
#10500
0$
#10750
1$
#11000
0$
#11250
1$
#11500
0$
#11750
1$
#12000
0$
#12250
1$
#12500
0$
#12750
1$
#13000
0$
#13250
1$
#13500
0$
#13750
1$
#14000
0$
#14250
1$
#14500
0$
#14750
1$
#15000
0$
#15250
1$
#15500
0$
#15750
1$
#16000
0$
#16250
1$
#16500
0$
#16750
1$
#17000
0$
#17250
1$
#17500
0$
#17750
1$
#18000
0$
#18250
1$
#18500
0$
#18750
1$
#19000
0$
#19250
1$
#19500
0$
#19750
1$
#20000
0$
b1 )
b1111111111111111111111111111111 '
b1111111111111111111111111111111 +
b100 *
b1111111111111111111111111111111 &
0%
#20250
1$
#20500
0$
b10 )
b111100110111100001110000100110 '
b111100110111100001110000100110 +
b111100110111100001110000100110 &
#20750
b1111111111111111111111111111111111111111111110000010000011101100 !
b1111111111111111111111111111111111111111111110000010000011101100 -
1$
#21000
0$
b11 )
b11110011110001101110111100111000 '
b11110011110001101110111100111000 +
b11110011110001101110111100111000 &
#21250
b1111111111111111111111111111111111111111110111010111010001000110 !
b1111111111111111111111111111111111111111110111010111010001000110 -
1$
#21500
0$
b100 )
b100101100111100100011000001000 '
b100101100111100100011000001000 +
b100101100111100100011000001000 &
#21750
b1111111111111111111111111111111111111111101000000100100100011110 !
b1111111111111111111111111111111111111111101000000100100100011110 -
1$
#22000
0$
b101 )
b1010011110001101110111100110110 '
b1010011110001101110111100110110 +
b1010011110001101110111100110110 &
#22250
b1111111111111111111111111111111111111111001010001010101011000100 !
b1111111111111111111111111111111111111111001010001010101011000100 -
1$
#22500
0$
b110 )
b0 '
b0 +
b0 &
#22750
b1111111111111111111111111111111111111110010111000101101110010010 !
b1111111111111111111111111111111111111110010111000101101110010010 -
1$
#23000
0$
b111 )
b10101100001110010001000011001010 '
b10101100001110010001000011001010 +
b10101100001110010001000011001010 &
#23250
b1111111111111111111111111111111111111101001001111011001001010010 !
b1111111111111111111111111111111111111101001001111011001001010010 -
1$
#23500
0$
b1000 )
b11011010011000011011100111111000 '
b11011010011000011011100111111000 +
b11011010011000011011100111111000 &
#23750
b1111111111111111111111111111111111111011100010010101101001101000 !
b1111111111111111111111111111111111111011100010010101101001101000 -
1$
#24000
0$
b1001 )
b1100001110010001000011001000 '
b1100001110010001000011001000 +
b1100001110010001000011001000 &
#24250
b1111111111111111111111111111111111111001100110000101001110101010 !
b1111111111111111111111111111111111111001100110000101001110101010 -
1$
#24500
0$
b1010 )
b11000011001000011110001111011010 '
b11000011001000011110001111011010 +
b11000011001000011110001111011010 &
#24750
b1111111111111111111111111111111111110111100011001110011010010110 !
b1111111111111111111111111111111111110111100011001110011010010110 -
1$
#25000
0$
b1011 )
b10000000000000000000000000000001 '
b10000000000000000000000000000001 +
b10000000000000000000000000000001 &
#25250
b1111111111111111111111111111111111110101110000101011001010110010 !
b1111111111111111111111111111111111110101110000101011001010110010 -
1$
#25500
0$
b1100 )
b11000011001000011110001111011010 '
b11000011001000011110001111011010 +
b11000011001000011110001111011010 &
#25750
b1111111111111111111111111111111111110100101100000001010101000011 !
b1111111111111111111111111111111111110100101100000001010101000011 -
1$
#26000
0$
b1101 )
b1100001110010001000011001000 '
b1100001110010001000011001000 +
b1100001110010001000011001000 &
#26250
b1111111111111111111111111111111111110100110011010111000110101101 !
b1111111111111111111111111111111111110100110011010111000110101101 -
1$
#26500
0$
b1110 )
b11011010011000011011100111111000 '
b11011010011000011011100111111000 +
b11011010011000011011100111111000 &
#26750
b1111111111111111111111111111111111110110011110011011001111000111 !
b1111111111111111111111111111111111110110011110011011001111000111 -
1$
#27000
0$
b1111 )
b10101100001110010001000011001010 '
b10101100001110010001000011001010 +
b10101100001110010001000011001010 &
#27250
b1111111111111111111111111111111111111001110111010110101111000011 !
b1111111111111111111111111111111111111001110111010110101111000011 -
1$
#27500
0$
b10000 )
b0 '
b0 +
b0 &
#27750
b1111111111111111111111111111111111111110110100101100111110101000 !
b1111111111111111111111111111111111111110110100101100111110101000 -
1$
#28000
0$
b10001 )
b1010011110001101110111100110110 '
b1010011110001101110111100110110 +
b1010011110001101110111100110110 &
#28250
b100110101111010001100101000 !
b100110101111010001100101000 -
1$
#28500
0$
b10010 )
b100101100111100100011000001000 '
b100101100111100100011000001000 +
b100101100111100100011000001000 &
#28750
b1011000110001100101100001100 !
b1011000110001100101100001100 -
1$
#29000
0$
b10011 )
b11110011110001101110111100111000 '
b11110011110001101110111100111000 +
b11110011110001101110111100111000 &
#29250
b10000100101010011100010110111 !
b10000100101010011100010110111 -
1$
#29500
0$
b10100 )
b111100110111100001110000100110 '
b111100110111100001110000100110 +
b111100110111100001110000100110 &
#29750
b10100010100000010000001001101 !
b10100010100000010000001001101 -
1$
#30000
0$
b10101 )
b1111111111111111111111111111111 '
b1111111111111111111111111111111 +
b1111111111111111111111111111111 &
#30250
b10101100001010000110001010000 !
b10101100001010000110001010000 -
1$
#30500
0$
b10110 )
b111100110111100001110000100110 '
b111100110111100001110000100110 +
b111100110111100001110000100110 &
#30750
b10011110110000111010010001001 !
b10011110110000111010010001001 -
1$
#31000
0$
b10111 )
b11110011110001101110111100111000 '
b11110011110001101110111100111000 +
b11110011110001101110111100111000 &
#31250
b1111011101001000011101001011 !
b1111011101001000011101001011 -
1$
#31500
0$
b11000 )
b100101100111100100011000001000 '
b100101100111100100011000001000 +
b100101100111100100011000001000 &
#31750
b1001000001011000111101010100 !
b1001000001011000111101010100 -
1$
#32000
0$
b11001 )
b1010011110001101110111100110110 '
b1010011110001101110111100110110 +
b1010011110001101110111100110110 &
#32250
b1100100110011010010101110 !
b1100100110011010010101110 -
1$
#32500
0$
b11010 )
b0 '
b0 +
b0 &
#32750
b1111111111111111111111111111111111111010010001101110100101110101 !
b1111111111111111111111111111111111111010010001101110100101110101 -
1$
#33000
0$
b11011 )
b10101100001110010001000011001010 '
b10101100001110010001000011001010 +
b10101100001110010001000011001010 &
#33250
b1111111111111111111111111111111111110100001011001100001111001111 !
b1111111111111111111111111111111111110100001011001100001111001111 -
1$
#33500
0$
b11100 )
b11011010011000011011100111111000 '
b11011010011000011011100111111000 +
b11011010011000011011100111111000 &
#33750
b1111111111111111111111111111111111101111111111001010001110111001 !
b1111111111111111111111111111111111101111111111001010001110111001 -
1$
#34000
0$
b11101 )
b1100001110010001000011001000 '
b1100001110010001000011001000 +
b1100001110010001000011001000 &
#34250
b1111111111111111111111111111111111101101111110011011101101000111 !
b1111111111111111111111111111111111101101111110011011101101000111 -
1$
#34500
0$
b11110 )
b11000011001000011110001111011010 '
b11000011001000011110001111011010 +
b11000011001000011110001111011010 &
#34750
b1111111111111111111111111111111111101101111101111011011101011001 !
b1111111111111111111111111111111111101101111101111011011101011001 -
1$
#35000
0$
b11111 )
b10000000000000000000000000000001 '
b10000000000000000000000000000001 +
b10000000000000000000000000000001 &
#35250
b1111111111111111111111111111111111101111100000001101010011010100 !
b1111111111111111111111111111111111101111100000001101010011010100 -
1$
#35500
0$
b100000 )
b11000011001000011110001111011010 '
b11000011001000011110001111011010 +
b11000011001000011110001111011010 &
#35750
b1111111111111111111111111111111111110010000010101111011011000000 !
b1111111111111111111111111111111111110010000010101111011011000000 -
1$
#36000
0$
b100001 )
b1100001110010001000011001000 '
b1100001110010001000011001000 +
b1100001110010001000011001000 &
#36250
b1111111111111111111111111111111111110101001001111010001001001011 !
b1111111111111111111111111111111111110101001001111010001001001011 -
1$
#36500
0$
b100010 )
b11011010011000011011100111111000 '
b11011010011000011011100111111000 +
b11011010011000011011100111111000 &
#36750
b1111111111111111111111111111111111111000101000110111001111111110 !
b1111111111111111111111111111111111111000101000110111001111111110 -
1$
#37000
0$
b100011 )
b10101100001110010001000011001010 '
b10101100001110010001000011001010 +
b10101100001110010001000011001010 &
#37250
b1111111111111111111111111111111111111100100010000011011100000001 !
b1111111111111111111111111111111111111100100010000011011100000001 -
1$
#37500
0$
b100100 )
b0 '
b0 +
b0 &
#37750
b111111001001001010110010 !
b111111001001001010110010 -
1$
#38000
0$
b100101 )
b1010011110001101110111100110110 '
b1010011110001101110111100110110 +
b1010011110001101110111100110110 &
#38250
b110000011010001001111001000 !
b110000011010001001111001000 -
1$
#38500
0$
b100110 )
b100101100111100100011000001000 '
b100101100111100100011000001000 +
b100101100111100100011000001000 &
#38750
b1011011110101001000100100111 !
b1011011110101001000100100111 -
1$
#39000
0$
b100111 )
b11110011110001101110111100111000 '
b11110011110001101110111100111000 +
b11110011110001101110111100111000 &
#39250
b10000101000110111110111110011 !
b10000101000110111110111110011 -
1$
#39500
0$
b101000 )
b111100110111100001110000100110 '
b111100110111100001110000100110 +
b111100110111100001110000100110 &
#39750
b10100100100101000101000011000 !
b10100100100101000101000011000 -
1$
#40000
0$
b101001 )
b1111111111111111111111111111111 '
b1111111111111111111111111111111 +
b1111111111111111111111111111111 &
#40250
b10110001101001001100010110101 !
b10110001101001001100010110101 -
1$
#40500
0$
b101010 )
b111100110111100001110000100110 '
b111100110111100001110000100110 +
b111100110111100001110000100110 &
#40750
b10100101011110111000101111100 !
b10100101011110111000101111100 -
1$
#41000
0$
b101011 )
b11110011110001101110111100111000 '
b11110011110001101110111100111000 +
b11110011110001101110111100111000 &
#41250
b1111101111100110001001001000 !
b1111101111100110001001001000 -
1$
#41500
0$
b101100 )
b100101100111100100011000001000 '
b100101100111100100011000001000 +
b100101100111100100011000001000 &
#41750
b111111100000001110100101010 !
b111111100000001110100101010 -
1$
#42000
0$
b101101 )
b1010011110001101110111100110110 '
b1010011110001101110111100110110 +
b1010011110001101110111100110110 &
#42250
b1111111111111111111111111111111111111110101010111010111011000000 !
b1111111111111111111111111111111111111110101010111010111011000000 -
1$
#42500
0$
b101110 )
b0 '
b0 +
b0 &
#42750
b1111111111111111111111111111111111110101111101111000111001000100 !
b1111111111111111111111111111111111110101111101111000111001000100 -
1$
#43000
0$
b101111 )
b10101100001110010001000011001010 '
b10101100001110010001000011001010 +
b10101100001110010001000011001010 &
#43250
b1111111111111111111111111111111111110000000010100111101010101110 !
b1111111111111111111111111111111111110000000010100111101010101110 -
1$
#43500
0$
b110000 )
b11011010011000011011100111111000 '
b11011010011000011011100111111000 +
b11011010011000011011100111111000 &
#43750
b1111111111111111111111111111111111101110101110110111001100010111 !
b1111111111111111111111111111111111101110101110110111001100010111 -
1$
#44000
0$
b110001 )
b1100001110010001000011001000 '
b1100001110010001000011001000 +
b1100001110010001000011001000 &
#44250
b1111111111111111111111111111111111110010111101111011101100011100 !
b1111111111111111111111111111111111110010111101111011101100011100 -
1$
#44500
0$
b110010 )
b11000011001000011110001111011010 '
b11000011001000011110001111011010 +
b11000011001000011110001111011010 &
#44750
b1111111111111111111111111111111111111100011011001100010001101010 !
b1111111111111111111111111111111111111100011011001100010001101010 -
1$
#45000
0$
b110011 )
b10000000000000000000000000000001 '
b10000000000000000000000000000001 +
b10000000000000000000000000000001 &
#45250
b1001100000011010001000111110 !
b1001100000011010001000111110 -
1$
#45500
0$
b110100 )
b11000011001000011110001111011010 '
b11000011001000011110001111011010 +
b11000011001000011110001111011010 &
#45750
b10111101000011000011010110011 !
b10111101000011000011010110011 -
1$
#46000
0$
b110101 )
b1100001110010001000011001000 '
b1100001110010001000011001000 +
b1100001110010001000011001000 &
#46250
b100011110001110101101001010011 !
b100011110001110101101001010011 -
1$
#46500
0$
b110110 )
b11011010011000011011100111111000 '
b11011010011000011011100111111000 +
b11011010011000011011100111111000 &
#46750
b101011001011010000001110101011 !
b101011001011010000001110101011 -
1$
#47000
0$
b110111 )
b10101100001110010001000011001010 '
b10101100001110010001000011001010 +
b10101100001110010001000011001010 &
#47250
b101011111100010001001101101111 !
b101011111100010001001101101111 -
1$
#47500
0$
b111000 )
b0 '
b0 +
b0 &
