ParallelFilter_L=2/filter.sv
`timescale 1ns / 1ps

module filter(
  input logic clk,
  input logic rst,
  input logic signed [31:0] x_in,
  input logic signed [31:0] x_in1,
  output logic signed [63:0] y_out,
  output logic signed [63:0] y_out1
);

parameter NUM_TAPS = 102;

logic signed [31:0] coeffs [102:0];

always_comb begin 
  coeffs[0] = 32'b11111111111110000010000011101100;
  coeffs[1] = 32'b11111111111000010011001010000001;
  coeffs[2] = 32'b11111111101011100010111001111001;
  coeffs[3] = 32'b11111111010011101111001000101101;
  coeffs[4] = 32'b11111110101101101111000110001010;
  coeffs[5] = 32'b11111101110111110111100010111000;
  coeffs[6] = 32'b11111100110100010100110110110111;
  coeffs[7] = 32'b11111011101001011101101101010111;
  coeffs[8] = 32'b11111010100010100111011001000011;
  coeffs[9] = 32'b11111001101101111111100111111111;
  coeffs[10] = 32'b11111001011010011101011111111110;
  coeffs[11] = 32'b11111001110010111111111101010011;
  coeffs[12] = 32'b11111010111011010101111011010111;
  coeffs[13] = 32'b11111100101100101101111001110001;
  coeffs[14] = 32'b11111110110110000001000110111110;
  coeffs[15] = 32'b00000000111110000010100110001000;
  coeffs[16] = 32'b00000010101001011010110110000000;
  coeffs[17] = 32'b00000011100001010010111010001011;
  coeffs[18] = 32'b00000011011010011010010100001110;
  coeffs[19] = 32'b00000010011000111100101011100000;
  coeffs[20] = 32'b00000000110000110111000110011101;
  coeffs[21] = 32'b11111111000000110111110001011111;
  coeffs[22] = 32'b11111101101010010011111101110010;
  coeffs[23] = 32'b11111101000110111111001100000111;
  coeffs[24] = 32'b11111101100001001011010110000110;
  coeffs[25] = 32'b11111110101111100111010001101110;
  coeffs[26] = 32'b00000000010111111110001101011110;
  coeffs[27] = 32'b00000001110110101110101010000111;
  coeffs[28] = 32'b00000010101010111010000001111100;
  coeffs[29] = 32'b00000010100001010010001000001011;
  coeffs[30] = 32'b00000001011011110110001011011000;
  coeffs[31] = 32'b11111111110010000001100101001000;
  coeffs[32] = 32'b11111110001001101010010111101101;
  coeffs[33] = 32'b11111101001010001001010011000111;
  coeffs[34] = 32'b11111101001110010001111000001100;
  coeffs[35] = 32'b11111110011001011000100000110110;
  coeffs[36] = 32'b00000000010100001011100010001100;
  coeffs[37] = 32'b00000010010010111000011111011011;
  coeffs[38] = 32'b00000011100011011111000110001011;
  coeffs[39] = 32'b00000011011111101001010101110110;
  coeffs[40] = 32'b00000001111100011111001111010010;
  coeffs[41] = 32'b11111111010010010111100110101101;
  coeffs[42] = 32'b11111100011001011001110000001110;
  coeffs[43] = 32'b11111010011010101010011011100011;
  coeffs[44] = 32'b11111010011010001100111111001111;
  coeffs[45] = 32'b11111101000000010110011101000010;
  coeffs[46] = 32'b00000010001001101111111101000100;
  coeffs[47] = 32'b00001001000011100100110011010111;
  coeffs[48] = 32'b00010000010110000000010110001000;
  coeffs[49] = 32'b00010110011010010110100111011111;
  coeffs[50] = 32'b00011001110110101011101000100111;
  coeffs[51] = 32'b00011001110110101011101000100111;
  coeffs[52] = 32'b00010110011010010110100111011111;
  coeffs[53] = 32'b00010000010110000000010110001000;
  coeffs[54] = 32'b00001001000011100100110011010111;
  coeffs[55] = 32'b00000010001001101111111101000100;
  coeffs[56] = 32'b11111101000000010110011101000010;
  coeffs[57] = 32'b11111010011010001100111111001111;
  coeffs[58] = 32'b11111010011010101010011011100011;
  coeffs[59] = 32'b11111100011001011001110000001110;
  coeffs[60] = 32'b11111111010010010111100110101101;
  coeffs[61] = 32'b00000001111100011111001111010010;
  coeffs[62] = 32'b00000011011111101001010101110110;
  coeffs[63] = 32'b00000011100011011111000110001011;
  coeffs[64] = 32'b00000010010010111000011111011011;
  coeffs[65] = 32'b00000000010100001011100010001100;
  coeffs[66] = 32'b11111110011001011000100000110110;
  coeffs[67] = 32'b11111101001110010001111000001100;
  coeffs[68] = 32'b11111101001010001001010011000111;
  coeffs[69] = 32'b11111110001001101010010111101101;
  coeffs[70] = 32'b11111111110010000001100101001000;
  coeffs[71] = 32'b00000001011011110110001011011000;
  coeffs[72] = 32'b00000010100001010010001000001011;
  coeffs[73] = 32'b00000010101010111010000001111100;
  coeffs[74] = 32'b00000001110110101110101010000111;
  coeffs[75] = 32'b00000000010111111110001101011110;
  coeffs[76] = 32'b11111110101111100111010001101110;
  coeffs[77] = 32'b11111101100001001011010110000110;
  coeffs[78] = 32'b11111101000110111111001100000111;
  coeffs[79] = 32'b11111101101010010011111101110010;
  coeffs[80] = 32'b11111111000000110111110001011111;
  coeffs[81] = 32'b00000000110000110111000110011101;
  coeffs[82] = 32'b00000010011000111100101011100000;
  coeffs[83] = 32'b00000011011010011010010100001110;
  coeffs[84] = 32'b00000011100001010010111010001011;
  coeffs[85] = 32'b00000010101001011010110110000000;
  coeffs[86] = 32'b00000000111110000010100110001000;
  coeffs[87] = 32'b11111110110110000001000110111110;
  coeffs[88] = 32'b11111100101100101101111001110001;
  coeffs[89] = 32'b11111010111011010101111011010111;
  coeffs[90] = 32'b11111001110010111111111101010011;
  coeffs[91] = 32'b11111001011010011101011111111110;
  coeffs[92] = 32'b11111001101101111111100111111111;
  coeffs[93] = 32'b11111010100010100111011001000011;
  coeffs[94] = 32'b11111011101001011101101101010111;
  coeffs[95] = 32'b11111100110100010100110110110111;
  coeffs[96] = 32'b11111101110111110111100010111000;
  coeffs[97] = 32'b11111110101101101111000110001010;
  coeffs[98] = 32'b11111111010011101111001000101101;
  coeffs[99] = 32'b11111111101011100010111001111001;
  coeffs[100] = 32'b11111111111000010011001010000001;
  coeffs[101] = 32'b11111111111110000010000011101100;
end

logic signed [31:0] even_samples [(NUM_TAPS / 2) - 1:0];
logic signed [31:0] odd_samples [(NUM_TAPS / 2) - 1:0];

logic signed [63:0] h0, h01, h1, h1_delayed;

always_ff @(posedge clk or posedge rst) begin
  if (rst) begin
    h1_delayed <= 0;
    for (int i=0; i < NUM_TAPS/2-1; i=i+1) begin
      even_samples[i] <= 0;
      odd_samples[i] <= 0;
    end 
  end else begin
    for (int i=NUM_TAPS/2-1; i > 0; i=i-1) begin
      even_samples[i] <= even_samples[i-1];
      odd_samples[i] <= odd_samples[i-1];
    end
    even_samples[0] <= x_in;
    odd_samples[0] <= x_in1;
    h1_delayed <= h1;
  end
end

always_comb begin
  h0 = 0;
  h01 = 0;
  h1 = 0;
  
  for (int i=0; i <= (NUM_TAPS/2) - 1; i=i+1) begin
    h0 += even_samples[i] * coeffs[2*i];
    h01 += (even_samples[i] + odd_samples[i]) * (coeffs[2*i] + coeffs[2*i+1]);
    h1 += odd_samples[i] * coeffs[2*i+1];
  end
end

assign y_out = (h0 + h1_delayed) >>> 31;
assign y_out1 = (h01 - h0 - h1) >>> 31;

endmodule

ParallelFilter_L=2/filter_tb.sv
`timescale 1ns / 1ps

module filter_tb;

  logic clk;
  logic rst;
  logic signed [31:0] x_in, x_in1;
  logic signed [63:0] y_out, y_out1;

  parameter CLK_PERIOD = 0.5; // 2GHz Clock
  parameter NUM_SAMPLES = 1000;

  filter uut(
    .clk(clk),
    .rst(rst),
    .x_in(x_in),
    .x_in1(x_in1),
    .y_out(y_out),
    .y_out1(y_out1)
  );


  // Start the clock
  initial begin
    clk = 0;
    forever #(CLK_PERIOD / 2) clk = ~clk;
  end

  integer file, status;
  integer sample_count;

  logic signed [31:0] sample_data, sample_data1;

  initial begin
    $dumpfile("filter_tb.vcd");
    $dumpvars(0, filter_tb);

    rst = 1;
    x_in = 0;
    sample_count = 0;

    // Open the raw signal data
    file = $fopen("../Python/InputSignals/cosine_wave_100MHz_500MHz.bin", "rb");
    if (file == 0) begin
        $display("Error: Unable to open file!");
        $finish;
    end

    #20 rst = 0;

    // Read and feed samples to the pipeline
    while (sample_count < NUM_SAMPLES) begin
      status = $fread(sample_data, file);
      if (status == 0) begin
        $display("Error: End of file reached or read error!");
        $finish;
      end
      
      status = $fread(sample_data1, file);
      if (status == 0) begin
        $display("Error: End of file reached or read error!");
        $finish;
      end

      x_in = sample_data;
      x_in1 = sample_data1;
      sample_count = sample_count + 2;
      #CLK_PERIOD;
    end

    $fclose(file);
    #100 $finish;
  end

endmodule

ParallelFilter_L=2/filter_tb.vcd
$date
	Tue Mar 18 18:24:06 2025
$end
$version
	Icarus Verilog
$end
$timescale
	1ps
$end
$scope module filter_tb $end
$var wire 64 ! y_out1 [63:0] $end
$var wire 64 " y_out [63:0] $end
$var real 1 # CLK_PERIOD $end
$var parameter 32 $ NUM_SAMPLES $end
$var reg 1 % clk $end
$var reg 1 & rst $end
$var reg 32 ' sample_data [31:0] $end
$var reg 32 ( sample_data1 [31:0] $end
$var reg 32 ) x_in [31:0] $end
$var reg 32 * x_in1 [31:0] $end
$var integer 32 + file [31:0] $end
$var integer 32 , sample_count [31:0] $end
$var integer 32 - status [31:0] $end
$scope module uut $end
$var wire 1 % clk $end
$var wire 1 & rst $end
$var wire 32 . x_in [31:0] $end
$var wire 32 / x_in1 [31:0] $end
$var wire 64 0 y_out1 [63:0] $end
$var wire 64 1 y_out [63:0] $end
$var parameter 32 2 NUM_TAPS $end
$var reg 64 3 h0 [63:0] $end
$var reg 64 4 h01 [63:0] $end
$var reg 64 5 h1 [63:0] $end
$var reg 64 6 h1_delayed [63:0] $end
$scope begin $ivl_for_loop0 $end
$var integer 32 7 i [31:0] $end
$upscope $end
$scope begin $ivl_for_loop1 $end
$var integer 32 8 i [31:0] $end
$upscope $end
$scope begin $ivl_for_loop2 $end
$var integer 32 9 i [31:0] $end
$upscope $end
$upscope $end
$upscope $end
$enddefinitions $end
$comment Show the parameter values. $end
$dumpall
b1100110 2
b1111101000 $
r0.5 #
$end
#0
$dumpvars
b110011 9
b0 8
b110010 7
b0 6
bx 5
bx 4
bx 3
bx 1
bx 0
bx /
b0 .
bx -
b0 ,
b10000000000000000000000000000011 +
bx *
b0 )
bx (
bx '
1&
0%
bx "
bx !
$end
#250
b110010 7
1%
#500
0%
#750
b110010 7
1%
#1000
0%
#1250
b110010 7
1%
#1500
0%
#1750
b110010 7
1%
#2000
0%
#2250
b110010 7
1%
#2500
0%
#2750
b110010 7
1%
#3000
0%
#3250
b110010 7
1%
#3500
0%
#3750
b110010 7
1%
#4000
0%
#4250
b110010 7
1%
#4500
0%
#4750
b110010 7
1%
#5000
0%
#5250
b110010 7
1%
#5500
0%
#5750
b110010 7
1%
#6000
0%
#6250
b110010 7
1%
#6500
0%
#6750
b110010 7
1%
#7000
0%
#7250
b110010 7
1%
#7500
0%
#7750
b110010 7
1%
#8000
0%
#8250
b110010 7
1%
#8500
0%
#8750
b110010 7
1%
#9000
0%
#9250
b110010 7
1%
#9500
0%
#9750
b110010 7
1%
#10000
0%
#10250
b110010 7
1%
#10500
0%
#10750
b110010 7
1%
#11000
0%
#11250
b110010 7
1%
#11500
0%
#11750
b110010 7
1%
#12000
0%
#12250
b110010 7
1%
#12500
0%
#12750
b110010 7
1%
#13000
0%
#13250
b110010 7
1%
#13500
0%
#13750
b110010 7
1%
#14000
0%
#14250
b110010 7
1%
#14500
0%
#14750
b110010 7
1%
#15000
0%
#15250
b110010 7
1%
#15500
0%
#15750
b110010 7
1%
#16000
0%
#16250
b110010 7
1%
#16500
0%
#16750
b110010 7
1%
#17000
0%
#17250
b110010 7
1%
#17500
0%
#17750
b110010 7
1%
#18000
0%
#18250
b110010 7
1%
#18500
0%
#18750
b110010 7
1%
#19000
0%
#19250
b110010 7
1%
#19500
0%
#19750
b110010 7
1%
#20000
0%
b10 ,
b111100110111100001110000100110 *
b111100110111100001110000100110 /
b1111111111111111111111111111111 )
b1111111111111111111111111111111 .
b111100110111100001110000100110 (
b100 -
b1111111111111111111111111111111 '
0&
#20250
b1111111111111111111111111111111111111111110111010111010001000110 !
b1111111111111111111111111111111111111111110111010111010001000110 0
b110011 9
b1111111111111000101011010001110010100100110100011001101100100110 5
b1111111111100011011101111011011000100100000011101111101011000001 4
b1111111111111100000100000111011000000000000001111101111100010100 3
bx 6
b0 8
1%
#20500
0%
b100 ,
b100101100111100100011000001000 *
b100101100111100100011000001000 /
b11110011110001101110111100111000 )
b11110011110001101110111100111000 .
b100101100111100100011000001000 (
b11110011110001101110111100111000 '
#20750
b1111111111111111111111111111111111111111001010001010101011000100 !
b1111111111111111111111111111111111111111001010001010101011000100 0
b1111111111111111111111111111111111111111101000000100100100011110 "
b1111111111111111111111111111111111111111101000000100100100011110 1
b110011 9
b1111111111010001011000000110011001111010101100011011100010110110 5
b1111111100111101001011010011101101000101101101110100110000111110 4
b1111111111010111011101110111001010011111110111010101100100100111 3
b1111111111111000101011010001110010100100110100011001101100100110 6
b0 8
1%
#21000
0%
b110 ,
b0 *
b0 /
b1010011110001101110111100110110 )
b1010011110001101110111100110110 .
b0 (
b1010011110001101110111100110110 '
#21250
b1111111111111111111111111111111111111101001001111011001001010010 !
b1111111111111111111111111111111111111101001001111011001001010010 0
b1111111111111111111111111111111111111110010111000101101110010010 "
b1111111111111111111111111111111111111110010111000101101110010010 1
b110011 9
b1111111101100100100000110110001101111001011001011110101010111000 5
b1111110101010101001010011110111110001011001010010111011100001000 4
b1111111101011100110011010110001011111000111101110111010110110110 3
b1111111111010001011000000110011001111010101100011011100010110110 6
b0 8
1%
#21500
0%
b1000 ,
b11011010011000011011100111111000 *
b11011010011000011011100111111000 /
b10101100001110010001000011001010 )
b10101100001110010001000011001010 .
b11011010011000011011100111111000 (
b10101100001110010001000011001010 '
#21750
b1111111111111111111111111111111111111001100110000101001110101010 !
b1111111111111111111111111111111111111001100110000101001110101010 0
b1111111111111111111111111111111111111011100010010101101001101000 "
b1111111111111111111111111111111111111011100010010101101001101000 1
b110011 9
b1111111010101011100110110100101011011000001001010100111010100010 5
b1111100111010111111011101111000101000100110110011100100100100100 4
b1111111001100000001010011101000011101110100010101101110100110111 3
b1111111101100100100000110110001101111001011001011110101010111000 6
b0 8
1%
#22000
0%
b1010 ,
b11000011001000011110001111011010 *
b11000011001000011110001111011010 /
b1100001110010001000011001000 )
b1100001110010001000011001000 .
b11000011001000011110001111011010 (
b1100001110010001000011001000 '
#22250
b1111111111111111111111111111111111110101110000101011001010110010 !
b1111111111111111111111111111111111110101110000101011001010110010 0
b1111111111111111111111111111111111110111100011001110011010010110 "
b1111111111111111111111111111111111110111100011001110011010010110 1
b110011 9
b1111110111111111010010101010101110111011010111000010101000000100 5
b1111010111111011011111000000010100001000101101100000101110111100 4
b1111110100011010110110000000000001000111111001101101111110111011 3
b1111111010101011100110110100101011011000001001010100111010100010 6
b0 8
1%
#22500
0%
b1100 ,
b10000000000000000000000000000001 )
b10000000000000000000000000000001 .
b10000000000000000000000000000001 '
#22750
b1111111111111111111111111111111111110100110011010111000110101101 !
b1111111111111111111111111111111111110100110011010111000110101101 0
b1111111111111111111111111111111111110100101100000001010101000011 "
b1111111111111111111111111111111111110100101100000001010101000011 1
b110011 9
b1111111000011011100100101111101010100101000100011111010010110110 5
b1111010011011011000010111100011110000000111000111111000001111000 4
b1111110001011000101111111111010111101001011010110000011110011100 3
b1111110111111111010010101010101110111011010111000010101000000100 6
b0 8
1%
#23000
0%
b1110 ,
b11011010011000011011100111111000 *
b11011010011000011011100111111000 /
b1100001110010001000011001000 )
b1100001110010001000011001000 .
b11011010011000011011100111111000 (
b1100001110010001000011001000 '
#23250
b1111111111111111111111111111111111111001110111010110101111000011 !
b1111111111111111111111111111111111111001110111010110101111000011 0
b1111111111111111111111111111111111110110011110011011001111000111 "
b1111111111111111111111111111111111110110011110011011001111000111 1
b110011 9
b1111111110100001100001001101111000001010110011011010010010100000 5
b1111100110110001100000011010100011101001001110011010001010110110 4
b1111110100100001010001101110100100111101011001110011111011101010 3
b1111111000011011100100101111101010100101000100011111010010110110 6
b0 8
1%
#23500
0%
b10000 ,
b0 *
b0 /
b10101100001110010001000011001010 )
b10101100001110010001000011001010 .
b0 (
b10101100001110010001000011001010 '
#23750
b100110101111010001100101000 !
b100110101111010001100101000 0
b1111111111111111111111111111111111111110110100101100111110101000 "
b1111111111111111111111111111111111111110110100101100111110101000 1
b110011 9
b1001001111011111111001001111000110100001110101110000011110 5
b10010000011001101000001110111010100011000100111111100001100 4
b1111111111000111111000101111010111111000000011110100100111111110 3
b1111111110100001100001001101111000001010110011011010010010100000 6
b0 8
1%
#24000
0%
b10010 ,
b100101100111100100011000001000 *
b100101100111100100011000001000 /
b1010011110001101110111100110110 )
b1010011110001101110111100110110 .
b100101100111100100011000001000 (
b1010011110001101110111100110110 '
#24250
b10000100101010011100010110111 !
b10000100101010011100010110111 0
b1011000110001100101100001100 "
b1011000110001100101100001100 1
b110011 9
b10010110110110011110101111101110010000110011001110111001110 5
b1000000111110010100011010110110000010010000111011010001001001 4
b1100111100111001011111001000111001100011000101010111110111 3
b1001001111011111111001001111000110100001110101110000011110 6
b0 8
1%
#24500
0%
b10100 ,
b111100110111100001110000100110 *
b111100110111100001110000100110 /
b11110011110001101110111100111000 )
b11110011110001101110111100111000 .
b111100110111100001110000100110 (
b11110011110001101110111100111000 '
#24750
b10101100001010000110001010000 !
b10101100001010000110001010000 0
b10100010100000010000001001101 "
b10100010100000010000001001101 1
b110011 9
b10100001100010110101101110010100000001110110001010110111010 5
b1010101000000001000011100110001100011011111110000010000000000 4
b10101110001010000001100011101010010110101111111001101100001 3
b10010110110110011110101111101110010000110011001110111001110 6
b0 8
1%
#25000
0%
b10110 ,
b1111111111111111111111111111111 )
b1111111111111111111111111111111 .
b1111111111111111111111111111111 '
#25250
b1111011101001000011101001011 !
b1111011101001000011101001011 0
b10011110110000111010010001001 "
b10011110110000111010010001001 1
b110011 9
b1010100110110000110101011000000110010110101001111101011110 5
b111101000000111001100110001111000101101000101000010001100010 4
b10011011111110111110110100000011001111011010011010010111011 3
b10100001100010110101101110010100000001110110001010110111010 6
b0 8
1%
#25500
0%
b11000 ,
b100101100111100100011000001000 *
b100101100111100100011000001000 /
b11110011110001101110111100111000 )
b11110011110001101110111100111000 .
b100101100111100100011000001000 (
b11110011110001101110111100111000 '
#25750
b1100100110011010010101110 !
b1100100110011010010101110 0
b1001000001011000111101010100 "
b1001000001011000111101010100 1
b110011 9
b1111111011001001111111001110111111011110110000001000111011011010 5
b101101111100110111001101101010011101010010000011010011101 4
b111011100000001000101010001100001101011110111010101100000 3
b1010100110110000110101011000000110010110101001111101011110 6
b0 8
1%
#26000
0%
b11010 ,
b0 *
b0 /
b1010011110001101110111100110110 )
b1010011110001101110111100110110 .
b0 (
b1010011110001101110111100110110 '
#26250
b1111111111111111111111111111111111110100001011001100001111001111 !
b1111111111111111111111111111111111110100001011001100001111001111 0
b1111111111111111111111111111111111111010010001101110100101110101 "
b1111111111111111111111111111111111111010010001101110100101110101 1
b110011 9
b1111101111000111001000011111011000110010010001011100001011001100 5
b1111010000110110111110111010100010100110111011101011110011110010 4
b1111111001011001011101111100101010111010001001011000001010010110 3
b1111111011001001111111001110111111011110110000001000111011011010 6
b0 8
1%
#26500
0%
b11100 ,
b11011010011000011011100111111000 *
b11011010011000011011100111111000 /
b10101100001110010001000011001010 )
b10101100001110010001000011001010 .
b11011010011000011011100111111000 (
b10101100001110010001000011001010 '
#26750
b1111111111111111111111111111111111101101111110011011101101000111 !
b1111111111111111111111111111111111101101111110011011101101000111 0
b1111111111111111111111111111111111101111111111001010001110111001 "
b1111111111111111111111111111111111101111111111001010001110111001 1
b110011 9
b1111101100011110100000000111011001111001110010110011001101110100 5
b1110111001010010100011100000000010111001110111111001010011101010 4
b1111110000110111001011111110011010001010100100001010111011011001 3
b1111101111000111001000011111011000110010010001011100001011001100 6
b0 8
1%
#27000
0%
b11110 ,
b11000011001000011110001111011010 *
b11000011001000011110001111011010 /
b1100001110010001000011001000 )
b1100001110010001000011001000 .
b11000011001000011110001111011010 (
b1100001110010001000011001000 '
#27250
b1111111111111111111111111111111111101111100000001101010011010100 !
b1111111111111111111111111111111111101111100000001101010011010100 0
b1111111111111111111111111111111111101101111101111011011101011001 "
b1111111111111111111111111111111111101101111101111011011101011001 1
b110011 9
b1111110001111011100110111011011010101100111011110000110111001110 5
b1111000000011001011000010101011110001110111111001110100001100101 4
b1111101111011101010110110011011001111100001011100001000110010011 3
b1111101100011110100000000111011001111001110010110011001101110100 6
b0 8
1%
#27500
0%
b100000 ,
b10000000000000000000000000000001 )
b10000000000000000000000000000001 .
b10000000000000000000000000000001 '
#27750
b1111111111111111111111111111111111110101001001111010001001001011 !
b1111111111111111111111111111111111110101001001111010001001001011 0
b1111111111111111111111111111111111110010000010101111011011000000 "
b1111111111111111111111111111111111110010000010101111011011000000 1
b110011 9
b1111111010001001111100111111010011100101010101001000010100110000 5
b1111010110100111101001001100010000100101011001010101000111000110 4
b1111110010001001110111111010100101111000100101010100110000101101 3
b1111110001111011100110111011011010101100111011110000110111001110 6
b0 8
1%
#28000
0%
b100010 ,
b11011010011000011011100111111000 *
b11011010011000011011100111111000 /
b1100001110010001000011001000 )
b1100001110010001000011001000 .
b11011010011000011011100111111000 (
b1100001110010001000011001000 '
#28250
b1111111111111111111111111111111111111100100010000011011100000001 !
b1111111111111111111111111111111111111100100010000011011100000001 0
b1111111111111111111111111111111111111000101000110111001111111110 "
b1111111111111111111111111111111111111000101000110111001111111110 1
b110011 9
b10000111100000100001001111110100000010000011011001100100 5
b1111110010010011011000111001111011111110110111001011010011010011 4
b1111110111000111110001100000101000100111011110000100001011110111 3
b1111111010001001111100111111010011100101010101001000010100110000 6
b0 8
1%
#28500
0%
b100100 ,
b0 *
b0 /
b10101100001110010001000011001010 )
b10101100001110010001000011001010 .
b0 (
b10101100001110010001000011001010 '
#28750
b110000011010001001111001000 !
b110000011010001001111001000 0
b111111001001001010110010 "
b111111001001001010110010 1
b110011 9
b1010011100101010011101000010110111110100011100011100001110 5
b10110011001111110101111101000111000010110010000000110010000 4
b1111111111110110110001110100010100111010010000000101001100001110 3
b10000111100000100001001111110100000010000011011001100100 6
b0 8
1%
#29000
0%
b100110 ,
b100101100111100100011000001000 *
b100101100111100100011000001000 /
b1010011110001101110111100110110 )
b1010011110001101110111100110110 .
b100101100111100100011000001000 (
b1010011110001101110111100110110 '
#29250
b10000101000110111110111110011 !
b10000101000110111110111110011 0
b1011011110101001000100100111 "
b1011011110101001000100100111 1
b110011 9
b10010011111101100110011111000011001010011110011010011011100 5
b1000000010010000100001111101100110000111001011011110000011111 4
b1100100000100111101100001101000001001100100100000110001001 3
b1010011100101010011101000010110111110100011100011100001110 6
b0 8
1%
#29500
0%
b101000 ,
b111100110111100001110000100110 *
b111100110111100001110000100110 /
b11110011110001101110111100111000 )
b11110011110001101110111100111000 .
b111100110111100001110000100110 (
b11110011110001101110111100111000 '
#29750
b10110001101001001100010110101 !
b10110001101001001100010110101 0
b10100100100101000101000011000 "
b10100100100101000101000011000 1
b110011 9
b10100100111100111000010011111101111100001110111100110100110 5
b1010111101011011110100101000011110010100001110110010000010100 4
b10110101001100100011100111001000110110011100000111111001100 3
b10010011111101100110011111000011001010011110011010011011100 6
b0 8
1%
#30000
0%
b101010 ,
b1111111111111111111111111111111 )
b1111111111111111111111111111111 .
b1111111111111111111111111111111 '
#30250
b1111101111100110001001001000 !
b1111101111100110001001001000 0
b10100101011110111000101111100 "
b10100101011110111000101111100 1
b110011 9
b1010110111011000000011100011011011111100101000011011110100 5
b111111000110101011011111001101000010000000111110000101111011 4
b10100110000000111001001011001001001000101011110001110010001 3
b10100100111100111000010011111101111100001110111100110100110 6
b0 8
1%
#30500
0%
b101100 ,
b100101100111100100011000001000 *
b100101100111100100011000001000 /
b11110011110001101110111100111000 )
b11110011110001101110111100111000 .
b100101100111100100011000001000 (
b11110011110001101110111100111000 '
#30750
b1111111111111111111111111111111111111110101010111010111011000000 !
b1111111111111111111111111111111111111110101010111010111011000000 0
b111111100000001110100101010 "
b111111100000001110100101010 1
b110011 9
b1111111000010101000101001111100100011011110001100011110111011010 5
b1111111010101011100110101011010111001111111000111001100111001010 4
b101000000101011100101110001010110101000101101010100010101 3
b1010110111011000000011100011011011111100101000011011110100 6
b0 8
1%
#31000
0%
b101110 ,
b0 *
b0 /
b1010011110001101110111100110110 )
b1010011110001101110111100110110 .
b0 (
b1010011110001101110111100110110 '
#31250
b1111111111111111111111111111111111110000000010100111101010101110 !
b1111111111111111111111111111111111110000000010100111101010101110 0
b1111111111111111111111111111111111110101111101111000111001000100 "
b1111111111111111111111111111111111110101111101111000111001000100 1
b110011 9
b1111101011001011111000010110101000001001010110001111111110100100 5
b1110111110110111110100001110101000111011110110110010000011011111 4
b1111110011100110101100100010100100011011111111011100001110001101 3
b1111111000010101000101001111100100011011110001100011110111011010 6
b0 8
1%
#31500
0%
b110000 ,
b11011010011000011011100111111000 *
b11011010011000011011100111111000 /
b10101100001110010001000011001010 )
b10101100001110010001000011001010 .
b11011010011000011011100111111000 (
b10101100001110010001000011001010 '
#31750
b1111111111111111111111111111111111110010111101111011101100011100 !
b1111111111111111111111111111111111110010111101111011101100011100 0
b1111111111111111111111111111111111101110101110110111001100010111 "
b1111111111111111111111111111111111101110101110110111001100010111 1
b110011 9
b1111110001011100111110110011010110010111110111101100101000110010 5
b1111001001101010101100001110010110001111110100010011000110111110 4
b1111110010010001110110000010000111100111011111100101101010111011 3
b1111101011001011111000010110101000001001010110001111111110100100 6
b0 8
1%
#32000
0%
b110010 ,
b11000011001000011110001111011010 *
b11000011001000011110001111011010 /
b1100001110010001000011001000 )
b1100001110010001000011001000 .
b11000011001000011110001111011010 (
b1100001110010001000011001000 '
#32250
b1001100000011010001000111110 !
b1001100000011010001000111110 0
b1111111111111111111111111111111111111100011011001100010001101010 "
b1111111111111111111111111111111111111100011011001100010001101010 1
b110011 9
b1001111110101001000101111011100101111011011000110101100110 5
b100100011000110111000111110101100111110111100100111100100101 4
b111011001011001101111111101110110100100111111001101010010 3
b1111110001011100111110110011010110010111110111101100101000110010 6
b0 8
1%
#32500
0%
b110100 ,
b10000000000000000000000000000001 )
b10000000000000000000000000000001 .
b10000000000000000000000000000001 '
#32750
b100011110001110101101001010011 !
b100011110001110101101001010011 0
b10111101000011000011010110011 "
b10111101000011000011010110011 1
b110011 9
b100001111101111010000111011000111111101000001100100000001100 5
b10001110110011101101001001101100011011010011000001101010100001 4
b100101010010000111101111101100000000110101011001100010100110 3
b1001111110101001000101111011100101111011011000110101100110 6
b0 8
1%
#33000
0%
b110110 ,
b11011010011000011011100111111000 *
b11011010011000011011100111111000 /
b1100001110010001000011001000 )
b1100001110010001000011001000 .
b11011010011000011011100111111000 (
b1100001110010001000011001000 '
#33250
b101011111100010001001101101111 !
b101011111100010001001101101111 0
b101011001011010000001110101011 "
b101011001011010000001110101011 1
b110011 9
b100011111011111011011110110101011000110000000011001100001010 5
b10110000001101000100010000010011100010100111101010110110001011 4
b110100011000100110010101111110111101011111111111101010100100 3
b100001111101111010000111011000111111101000001100100000001100 6
b0 8
1%
#33500
0%
b111000 ,
b0 *
b0 /
b10101100001110010001000011001010 )
b10101100001110010001000011001010 .
b0 (
b10101100001110010001000011001010 '
#33750
b11000101111000001111000011001 !
b11000101111000001111000011001 0
b100101100000110000101100111010 "
b100101100000110000101100111010 1
b110011 9
b1010101011101001110010101001110111101011100111101111010010 5
b1100011001111010011011110011011000001000010011111000101100000 4
b100111000101100101111010111110101000000100001000000100001110 3
b100011111011111011011110110101011000110000000011001100001010 6
b0 8
1%
#34000
0%
b111010 ,
b100101100111100100011000001000 *
b100101100111100100011000001000 /
b1010011110001101110111100110110 )
b1010011110001101110111100110110 .
b100101100111100100011000001000 (
b1010011110001101110111100110110 '
#34250
b1111111111111111111111111111111111110101000001001100100000001011 !
b1111111111111111111111111111111111110101000001001100100000001011 0
b111101001100101101010100110 "
b111101001100101101010100110 1
b110011 9
b1111100101111110111100111010100011001011011111101010111001010110 5
b1111010100101000110111011101011101011111100000010100000001111011 4
b100100111100001100010100011100000100000100111000100011011 3
b1010101011101001110010101001110111101011100111101111010010 6
b0 8
1%
#34500
0%
b111100 ,
b111100110111100001110000100110 *
b111100110111100001110000100110 /
b11110011110001101110111100111000 )
b11110011110001101110111100111000 .
b111100110111100001110000100110 (
b11110011110001101110111100111000 '
#34750
b1111111111111111111111111111111111010110001100000100001011011000 !
b1111111111111111111111111111111111010110001100000100001011011000 0
b1111111111111111111111111111111111100011101110010010010111010000 "
b1111111111111111111111111111111111100011101110010010010111010000 1
b110011 9
b1111001101000111001101110101111011111000010111101111101100011100 5
b1101011010111100111110000000101010011011111011111110100100001100 4
b1111100001011101100111110011111101110001011100101110000100000011 3
b1111100101111110111100111010100011001011011111101010111001010110 6
b0 8
1%
#35000
0%
b111110 ,
b1111111111111111111111111111111 )
b1111111111111111111111111111111 .
b1111111111111111111111111111111 '
#35250
b1111111111111111111111111111111111001011101101000101101101110100 !
b1111111111111111111111111111111111001011101101000101101101110100 0
b1111111111111111111111111111111111001101111111001111000010000100 "
b1111111111111111111111111111111111001101111111001111000010000100 1
b110011 9
b1111001100111101001010110000010101010110111101001101000101000000 5
b1100110011001110100110011010001011010000110110100110000000110100 4
b1111001110110111010000001110001100001111111010000111101000011111 3
b1111001101000111001101110101111011111000010111101111101100011100 6
b0 8
1%
#35500
0%
b1000000 ,
b100101100111100100011000001000 *
b100101100111100100011000001000 /
b11110011110001101110111100111000 )
b11110011110001101110111100111000 .
b100101100111100100011000001000 (
b11110011110001101110111100111000 '
